dlab_connect4/design_src/connect4.v
module connect4 (
    input clk,
    input rst_n,
    
    output reg  op_ready,
    input       op_valid,
    input       op_player_id,
    input [2:0] op_col_id,

    input       re_ready,
    output reg  re_valid,
    output reg  re_err,
    output reg  re_is_finished,
    output reg  re_winner,
    output reg  re_tie
);

localparam S_WAIT_OP  = 0,
           S_DROP     = 1,
           S_GO_JUDGE = 2,
           S_JUDGE    = 3,
           S_RE       = 4;



reg  op_ready_nxt;
reg  re_valid_nxt;
reg  re_err_nxt;
reg  re_is_finished_nxt;
reg  re_winner_nxt;
reg  re_tie_nxt;

reg [3:0] S, S_nxt;

reg [41:0] occupied/* verilator public */;
reg [41:0] whos/* verilator public */;
reg [41:0] occupied_nxt;
reg [41:0] whos_nxt;
reg player_id, player_id_nxt;
reg [2:0] col_id, col_id_nxt;
reg [2:0] row_id, row_id_nxt;

wire wj_op_ready;
reg wj_op_valid, wj_op_valid_nxt;

reg wj_re_ready, wj_re_ready_nxt;
wire wj_re_valid;
wire wj_re_is_finished;

win_judge wj (
    .clk(clk),
    .rst_n(rst_n),

    .occupied(occupied),
    .whos(whos),

    .op_ready(wj_op_ready),
    .op_valid(wj_op_valid),

    .re_ready(wj_re_ready),
    .re_valid(wj_re_valid),
    .re_is_finished(wj_re_is_finished)
);

reg op_fire, re_fire, wj_op_fire, wj_re_fire;
reg [6:0] col_full;

integer i;

always @(*) begin
    op_fire = op_ready & op_valid;
    re_fire = re_ready & re_valid;
    wj_op_fire = wj_op_ready & wj_op_valid;
    wj_re_fire = wj_re_ready & wj_re_valid;

    col_full = occupied[6:0];

    op_ready_nxt = op_ready;
    re_valid_nxt = re_valid;
    re_err_nxt = re_err;
    re_is_finished_nxt = re_is_finished;
    re_winner_nxt = re_winner;
    re_tie_nxt = re_tie;

    S_nxt = S;

    occupied_nxt = occupied;
    whos_nxt = whos;
    player_id_nxt = player_id;
    col_id_nxt = col_id;
    row_id_nxt = row_id;

    wj_op_valid_nxt = wj_op_valid;

    wj_re_ready_nxt = wj_re_ready;

    case (S)
        S_WAIT_OP: begin
            if (op_fire) begin
                op_ready_nxt = 0;

                player_id_nxt = op_player_id;
                col_id_nxt = op_col_id;
                if (col_full[op_col_id]) begin
                    re_valid_nxt = 1;
                    re_err_nxt = 1;
                    re_is_finished_nxt = 0;
                    re_winner_nxt = 0;
                    re_tie_nxt = 0;
                    S_nxt = S_RE;
                end
                else begin
                    {occupied_nxt[op_col_id], whos_nxt[op_col_id]} = {1'b1, op_player_id};
                    row_id_nxt = 0;
                    S_nxt = S_DROP;
                end
            end
        end
        S_DROP: begin
            if (row_id == 5 || occupied[(row_id+1) * 7 + col_id]) begin
                wj_op_valid_nxt = 1;
                S_nxt = S_GO_JUDGE;
            end
            else begin
                {occupied_nxt[ row_id    * 7 + col_id], whos_nxt[ row_id    * 7 + col_id]} = 2'b0;
                {occupied_nxt[(row_id+1) * 7 + col_id], whos_nxt[(row_id+1) * 7 + col_id]} = {1'b1, op_player_id};
                row_id_nxt = row_id + 1;
                S_nxt = S_DROP;
            end
        end
        S_GO_JUDGE: begin
            if (wj_op_fire) begin
                wj_re_ready_nxt = 1;

                wj_op_valid_nxt = 0;

                S_nxt = S_JUDGE;
            end
        end
        S_JUDGE: begin
            if (wj_re_fire) begin
                wj_re_ready_nxt = 0;

                re_valid_nxt = 1;
                re_err_nxt = 0;
                re_is_finished_nxt = wj_re_is_finished | (&col_full);
                re_tie_nxt = (&col_full) & ~wj_re_is_finished;
                re_winner_nxt = wj_re_is_finished ? player_id : 0;

                S_nxt = S_RE;
            end
        end
        S_RE: begin
            if (re_fire) begin
                op_ready_nxt = 1;

                re_valid_nxt = 0;
                re_err_nxt = 0;
                re_is_finished_nxt = 0;
                re_winner_nxt = 0;
                re_tie_nxt = 0;

                if (re_is_finished) begin
                    occupied_nxt = 42'b0;
                    whos_nxt = 42'b0;
                    player_id_nxt = 0;
                    col_id_nxt = 0;
                    row_id_nxt = 0;
                end

                S_nxt = S_WAIT_OP;
            end
        end
        default: begin
        end
    endcase
end

always @(posedge clk, negedge rst_n) begin
    if (~rst_n) begin
        S <= S_WAIT_OP;

        op_ready <= 1;
        re_valid <= 0;
        re_err <= 0;
        re_is_finished <= 0;
        re_winner <= 0;
        re_tie <= 0;

        occupied <= 42'b0;
        whos <= 42'b0;
        player_id <= 0;
        col_id <= 0;
        row_id <= 0;

        wj_op_valid <= 0;

        wj_re_ready <= 0;
    end
    else begin
        S <= S_nxt;

        op_ready <= op_ready_nxt;
        re_valid <= re_valid_nxt;
        re_err <= re_err_nxt;
        re_is_finished <= re_is_finished_nxt;
        re_winner <= re_winner_nxt;
        re_tie <= re_tie_nxt;

        occupied <= occupied_nxt;
        whos <= whos_nxt;
        player_id <= player_id_nxt;
        col_id <= col_id_nxt;
        row_id <= row_id_nxt;

        wj_op_valid <= wj_op_valid_nxt;

        wj_re_ready <= wj_re_ready_nxt;
    end
end

endmodule

module win_judge (
    input clk,
    input rst_n,

    input [41:0] occupied,
    input [41:0] whos,

    output reg  op_ready,
    input       op_valid,

    input       re_ready,
    output reg  re_valid,
    output reg  re_is_finished
);

localparam S_IDLE = 0,
           S_DETECT_V = 1,
           S_DETECT_H = 2,
           S_DETECT_RISE = 3,
           S_DETECT_FALL = 4,
           S_RE = 5;

reg op_ready_nxt;
reg re_valid_nxt;
reg re_is_finished_nxt;

reg [3:0] S, S_nxt;

reg [2:0] rlim, rlim_nxt;
reg [2:0] llim, llim_nxt;
reg [2:0] tlim, tlim_nxt;
reg [2:0] blim, blim_nxt;

reg [2:0] c, c_nxt;
reg [2:0] r, r_nxt;

reg op_fire, re_fire;

reg occupied_all;
reg whos_all;
reg [2:0] c0, c1, c2, c3, r0, r1, r2, r3;

always @(*) begin
    op_fire = op_ready & op_valid;
    re_fire = re_ready & re_valid;
    occupied_all = 0;
    whos_all = 0;
    c0 = 0; c1 = 0; c2 = 0; c3 = 0;
    r0 = 0; r1 = 0; r2 = 0; r3 = 0;

    op_ready_nxt = op_ready;
    re_valid_nxt = re_valid;
    re_is_finished_nxt = re_is_finished;

    S_nxt = S;

    rlim_nxt = rlim;
    llim_nxt = llim;
    tlim_nxt = tlim;
    blim_nxt = blim;

    c_nxt = c;
    r_nxt = r;

    case (S)
        S_IDLE: begin
            if (op_fire) begin
                op_ready_nxt = 0;
                
                rlim_nxt = 0;
                llim_nxt = 6;
                tlim_nxt = 0;
                blim_nxt = 2;

                c_nxt = rlim_nxt;
                r_nxt = tlim_nxt;

                S_nxt = S_DETECT_V;
            end
        end
        S_DETECT_V: begin
            c0 = c; r0 = r    ;
            c1 = c; r1 = r + 1;
            c2 = c; r2 = r + 2;
            c3 = c; r3 = r + 3;
            occupied_all = ( & {occupied[r0 * 7 + c0], occupied[r1 * 7 + c1], occupied[r2 * 7 + c2], occupied[r3 * 7 + c3]});
            whos_all     = ( & {whos    [r0 * 7 + c0], whos    [r1 * 7 + c1], whos    [r2 * 7 + c2], whos    [r3 * 7 + c3]}) |
                           (~| {whos    [r0 * 7 + c0], whos    [r1 * 7 + c1], whos    [r2 * 7 + c2], whos    [r3 * 7 + c3]});
            
            c_nxt = (c == llim) ? rlim : c + 1;
            r_nxt = (c == llim) ? r + 1 : r;

            if (occupied_all && whos_all) begin
                re_valid_nxt = 1;
                re_is_finished_nxt = 1;
                S_nxt = S_RE;
            end
            else begin
                if (c == llim && r == blim) begin
                    rlim_nxt = 0;
                    llim_nxt = 3;
                    tlim_nxt = 0;
                    blim_nxt = 5;

                    c_nxt = rlim_nxt;
                    r_nxt = tlim_nxt;

                    S_nxt = S_DETECT_H;
                end
            end
        end
        S_DETECT_H: begin
            c0 = c    ; r0 = r;
            c1 = c + 1; r1 = r;
            c2 = c + 2; r2 = r;
            c3 = c + 3; r3 = r;
            occupied_all = ( & {occupied[r0 * 7 + c0], occupied[r1 * 7 + c1], occupied[r2 * 7 + c2], occupied[r3 * 7 + c3]});
            whos_all     = ( & {whos    [r0 * 7 + c0], whos    [r1 * 7 + c1], whos    [r2 * 7 + c2], whos    [r3 * 7 + c3]}) |
                           (~| {whos    [r0 * 7 + c0], whos    [r1 * 7 + c1], whos    [r2 * 7 + c2], whos    [r3 * 7 + c3]});
            
            c_nxt = (c == llim) ? rlim : c + 1;
            r_nxt = (c == llim) ? r + 1 : r;

            if (occupied_all && whos_all) begin
                re_valid_nxt = 1;
                re_is_finished_nxt = 1;
                S_nxt = S_RE;
            end
            else begin
                if (c == llim && r == blim) begin
                    rlim_nxt = 0;
                    llim_nxt = 3;
                    tlim_nxt = 3;
                    blim_nxt = 5;

                    c_nxt = rlim_nxt;
                    r_nxt = tlim_nxt;

                    S_nxt = S_DETECT_RISE;
                end
            end
        end
        S_DETECT_RISE: begin
            c0 = c    ; r0 = r    ;
            c1 = c + 1; r1 = r - 1;
            c2 = c + 2; r2 = r - 2;
            c3 = c + 3; r3 = r - 3;
            occupied_all = ( & {occupied[r0 * 7 + c0], occupied[r1 * 7 + c1], occupied[r2 * 7 + c2], occupied[r3 * 7 + c3]});
            whos_all     = ( & {whos    [r0 * 7 + c0], whos    [r1 * 7 + c1], whos    [r2 * 7 + c2], whos    [r3 * 7 + c3]}) |
                           (~| {whos    [r0 * 7 + c0], whos    [r1 * 7 + c1], whos    [r2 * 7 + c2], whos    [r3 * 7 + c3]});
            
            c_nxt = (c == llim) ? rlim : c + 1;
            r_nxt = (c == llim) ? r + 1 : r;

            if (occupied_all && whos_all) begin
                re_valid_nxt = 1;
                re_is_finished_nxt = 1;
                S_nxt = S_RE;
            end
            else begin
                if (c == llim && r == blim) begin
                    rlim_nxt = 0;
                    llim_nxt = 3;
                    tlim_nxt = 0;
                    blim_nxt = 2;

                    c_nxt = rlim_nxt;
                    r_nxt = tlim_nxt;

                    S_nxt = S_DETECT_FALL;
                end
            end
        end
        S_DETECT_FALL: begin
            c0 = c    ; r0 = r    ;
            c1 = c + 1; r1 = r + 1;
            c2 = c + 2; r2 = r + 2;
            c3 = c + 3; r3 = r + 3;
            occupied_all = ( & {occupied[r0 * 7 + c0], occupied[r1 * 7 + c1], occupied[r2 * 7 + c2], occupied[r3 * 7 + c3]});
            whos_all     = ( & {whos    [r0 * 7 + c0], whos    [r1 * 7 + c1], whos    [r2 * 7 + c2], whos    [r3 * 7 + c3]}) |
                           (~| {whos    [r0 * 7 + c0], whos    [r1 * 7 + c1], whos    [r2 * 7 + c2], whos    [r3 * 7 + c3]});
            
            c_nxt = (c == llim) ? rlim : c + 1;
            r_nxt = (c == llim) ? r + 1 : r;

            if (occupied_all && whos_all) begin
                re_valid_nxt = 1;
                re_is_finished_nxt = 1;
                S_nxt = S_RE;
            end
            else begin
                if (c == llim && r == blim) begin
                    re_valid_nxt = 1;
                    re_is_finished_nxt = 0;
                    S_nxt = S_RE;
                end
            end
        end
        S_RE: begin
            if (re_fire) begin
                re_valid_nxt = 0;
                re_is_finished_nxt = 0;
                op_ready_nxt = 1;
                S_nxt = S_IDLE;
            end
        end
        default: begin
        end
    endcase
end

always @(posedge clk, negedge rst_n) begin
    if (~rst_n) begin
        op_ready <= 1;
        re_valid <= 0;
        re_is_finished <= 0;

        S <= S_IDLE;
        rlim <= 0;
        llim <= 0;
        tlim <= 0;
        blim <= 0;
        c    <= 0;
        r    <= 0;
    end
    else begin
        op_ready <= op_ready_nxt;
        re_valid <= re_valid_nxt;
        re_is_finished <= re_is_finished_nxt;

        S <= S_nxt;

        rlim <= rlim_nxt;
        llim <= llim_nxt;
        tlim <= tlim_nxt;
        blim <= blim_nxt;
        c <= c_nxt;
        r <= r_nxt;
    end
end

endmodule

dlab_connect4/sim_result/wave.vcd
$version Generated by VerilatedVcd $end
$timescale 1ps $end
 $scope module TOP $end
  $scope module connect4 $end
   $var wire 1 / clk $end
   $var wire 1 0 rst_n $end
   $var wire 1 1 op_ready $end
   $var wire 1 2 op_valid $end
   $var wire 1 3 op_player_id $end
   $var wire 3 4 op_col_id [2:0] $end
   $var wire 1 5 re_ready $end
   $var wire 1 6 re_valid $end
   $var wire 1 7 re_err $end
   $var wire 1 8 re_is_finished $end
   $var wire 1 9 re_winner $end
   $var wire 1 : re_tie $end
   $var wire 32 (! S_WAIT_OP [31:0] $end
   $var wire 32 )! S_DROP [31:0] $end
   $var wire 32 *! S_GO_JUDGE [31:0] $end
   $var wire 32 +! S_JUDGE [31:0] $end
   $var wire 32 ,! S_RE [31:0] $end
   $var wire 1 ; op_ready_nxt $end
   $var wire 1 < re_valid_nxt $end
   $var wire 1 = re_err_nxt $end
   $var wire 1 > re_is_finished_nxt $end
   $var wire 1 ? re_winner_nxt $end
   $var wire 1 @ re_tie_nxt $end
   $var wire 4 A S [3:0] $end
   $var wire 4 B S_nxt [3:0] $end
   $var wire 42 C occupied [41:0] $end
   $var wire 42 E whos [41:0] $end
   $var wire 42 G occupied_nxt [41:0] $end
   $var wire 42 I whos_nxt [41:0] $end
   $var wire 1 K player_id $end
   $var wire 1 L player_id_nxt $end
   $var wire 3 M col_id [2:0] $end
   $var wire 3 N col_id_nxt [2:0] $end
   $var wire 3 O row_id [2:0] $end
   $var wire 3 P row_id_nxt [2:0] $end
   $var wire 1 Q wj_op_ready $end
   $var wire 1 R wj_op_valid $end
   $var wire 1 S wj_op_valid_nxt $end
   $var wire 1 T wj_re_ready $end
   $var wire 1 U wj_re_ready_nxt $end
   $var wire 1 V wj_re_valid $end
   $var wire 1 W wj_re_is_finished $end
   $var wire 1 X op_fire $end
   $var wire 1 Y re_fire $end
   $var wire 1 Z wj_op_fire $end
   $var wire 1 [ wj_re_fire $end
   $var wire 7 \ col_full [6:0] $end
   $var wire 32 ] i [31:0] $end
   $scope module wj $end
    $var wire 1 ^ clk $end
    $var wire 1 _ rst_n $end
    $var wire 42 ` occupied [41:0] $end
    $var wire 42 b whos [41:0] $end
    $var wire 1 d op_ready $end
    $var wire 1 e op_valid $end
    $var wire 1 f re_ready $end
    $var wire 1 g re_valid $end
    $var wire 1 h re_is_finished $end
    $var wire 32 (! S_IDLE [31:0] $end
    $var wire 32 )! S_DETECT_V [31:0] $end
    $var wire 32 *! S_DETECT_H [31:0] $end
    $var wire 32 +! S_DETECT_RISE [31:0] $end
    $var wire 32 ,! S_DETECT_FALL [31:0] $end
    $var wire 32 -! S_RE [31:0] $end
    $var wire 1 i op_ready_nxt $end
    $var wire 1 j re_valid_nxt $end
    $var wire 1 k re_is_finished_nxt $end
    $var wire 4 l S [3:0] $end
    $var wire 4 m S_nxt [3:0] $end
    $var wire 3 n rlim [2:0] $end
    $var wire 3 o rlim_nxt [2:0] $end
    $var wire 3 p llim [2:0] $end
    $var wire 3 q llim_nxt [2:0] $end
    $var wire 3 r tlim [2:0] $end
    $var wire 3 s tlim_nxt [2:0] $end
    $var wire 3 t blim [2:0] $end
    $var wire 3 u blim_nxt [2:0] $end
    $var wire 3 v c [2:0] $end
    $var wire 3 w c_nxt [2:0] $end
    $var wire 3 x r [2:0] $end
    $var wire 3 y r_nxt [2:0] $end
    $var wire 1 z op_fire $end
    $var wire 1 { re_fire $end
    $var wire 1 | occupied_all $end
    $var wire 1 } whos_all $end
    $var wire 3 ~ c0 [2:0] $end
    $var wire 3 !! c1 [2:0] $end
    $var wire 3 "! c2 [2:0] $end
    $var wire 3 #! c3 [2:0] $end
    $var wire 3 $! r0 [2:0] $end
    $var wire 3 %! r1 [2:0] $end
    $var wire 3 &! r2 [2:0] $end
    $var wire 3 '! r3 [2:0] $end
   $upscope $end
  $upscope $end
  $var wire 1 # clk $end
  $var wire 1 $ rst_n $end
  $var wire 1 % op_ready $end
  $var wire 1 & op_valid $end
  $var wire 1 ' op_player_id $end
  $var wire 3 ( op_col_id [2:0] $end
  $var wire 1 ) re_ready $end
  $var wire 1 * re_valid $end
  $var wire 1 + re_err $end
  $var wire 1 , re_is_finished $end
  $var wire 1 - re_winner $end
  $var wire 1 . re_tie $end
 $upscope $end
$enddefinitions $end


#5
0#
0$
0%
0&
0'
b000 (
0)
0*
0+
0,
0-
0.
0/
00
01
02
03
b000 4
05
06
07
08
09
0:
0;
0<
0=
0>
0?
0@
b0000 A
b0000 B
b000000000000000000000000000000000000000000 C
b000000000000000000000000000000000000000000 E
b000000000000000000000000000000000000000000 G
b000000000000000000000000000000000000000000 I
0K
0L
b000 M
b000 N
b000 O
b000 P
0Q
0R
0S
0T
0U
0V
0W
0X
0Y
0Z
0[
b0000000 \
b00000000000000000000000000000000 ]
0^
0_
b000000000000000000000000000000000000000000 `
b000000000000000000000000000000000000000000 b
0d
0e
0f
0g
0h
0i
0j
0k
b0000 l
b0000 m
b000 n
b000 o
b000 p
b000 q
b000 r
b000 s
b000 t
b000 u
b000 v
b000 w
b000 x
b000 y
0z
0{
0|
0}
b000 ~
b000 !!
b000 "!
b000 #!
b000 $!
b000 %!
b000 &!
b000 '!
b00000000000000000000000000000000 (!
b00000000000000000000000000000001 )!
b00000000000000000000000000000010 *!
b00000000000000000000000000000011 +!
b00000000000000000000000000000100 ,!
b00000000000000000000000000000101 -!
#10
1#
1%
1/
11
1;
1Q
1^
1d
1i
#15
0#
0/
0^
#20
1#
1/
1^
#25
0#
1$
0/
10
0^
1_
#30
1#
1/
1^
#35
0#
0/
0^
#40
1#
1/
1^
#45
0#
1&
0/
12
0;
b0001 B
b000000000000000000000000000000000000000001 G
1X
0^
#50
1#
0%
1/
01
b0001 A
b000000000000000000000000000000000000000001 C
b000000000000000000000000000000000010000000 G
b001 P
0X
b0000001 \
1^
b000000000000000000000000000000000000000001 `
#55
0#
0&
1)
0/
02
15
0^
#60
1#
1/
b000000000000000000000000000000000010000000 C
b000000000000000000000000000100000000000000 G
b001 O
b010 P
b0000000 \
1^
b000000000000000000000000000000000010000000 `
#65
0#
0/
0^
#70
1#
1/
b000000000000000000000000000100000000000000 C
b000000000000000000001000000000000000000000 G
b010 O
b011 P
1^
b000000000000000000000000000100000000000000 `
#75
0#
0/
0^
#80
1#
1/
b000000000000000000001000000000000000000000 C
b000000000000010000000000000000000000000000 G
b011 O
b100 P
1^
b000000000000000000001000000000000000000000 `
#85
0#
0/
0^
#90
1#
1/
b000000000000010000000000000000000000000000 C
b000000100000000000000000000000000000000000 G
b100 O
b101 P
1^
b000000000000010000000000000000000000000000 `
#95
0#
0/
0^
#100
1#
1/
b0010 B
b000000100000000000000000000000000000000000 C
b101 O
1S
1^
b000000100000000000000000000000000000000000 `
#105
0#
0/
0^
#110
1#
1/
b0010 A
b0011 B
1R
0S
1U
1Z
1^
1e
0i
b0001 m
b110 q
b010 u
1z
#115
0#
0/
0^
#120
1#
1/
b0011 A
0Q
0R
1T
0Z
1^
0d
0e
1f
b0001 l
b110 p
b010 t
b001 w
0z
1}
b001 %!
b010 &!
b011 '!
#125
0#
0/
0^
#130
1#
1/
1^
b001 v
b010 w
b001 ~
b001 !!
b001 "!
b001 #!
#135
0#
0/
0^
#140
1#
1/
1^
b010 v
b011 w
b010 ~
b010 !!
b010 "!
b010 #!
#145
0#
0/
0^
#150
1#
1/
1^
b011 v
b100 w
b011 ~
b011 !!
b011 "!
b011 #!
#155
0#
0/
0^
#160
1#
1/
1^
b100 v
b101 w
b100 ~
b100 !!
b100 "!
b100 #!
#165
0#
0/
0^
#170
1#
1/
1^
b101 v
b110 w
b101 ~
b101 !!
b101 "!
b101 #!
#175
0#
0/
0^
#180
1#
1/
1^
b110 v
b000 w
b001 y
b110 ~
b110 !!
b110 "!
b110 #!
#185
0#
0/
0^
#190
1#
1/
1^
b000 v
b001 w
b001 x
b000 ~
b000 !!
b000 "!
b000 #!
b001 $!
b010 %!
b011 &!
b100 '!
#195
0#
0/
0^
#200
1#
1/
1^
b001 v
b010 w
b001 ~
b001 !!
b001 "!
b001 #!
#205
0#
0/
0^
#210
1#
1/
1^
b010 v
b011 w
b010 ~
b010 !!
b010 "!
b010 #!
#215
0#
0/
0^
#220
1#
1/
1^
b011 v
b100 w
b011 ~
b011 !!
b011 "!
b011 #!
#225
0#
0/
0^
#230
1#
1/
1^
b100 v
b101 w
b100 ~
b100 !!
b100 "!
b100 #!
#235
0#
0/
0^
#240
1#
1/
1^
b101 v
b110 w
b101 ~
b101 !!
b101 "!
b101 #!
#245
0#
0/
0^
#250
1#
1/
1^
b110 v
b000 w
b010 y
b110 ~
b110 !!
b110 "!
b110 #!
#255
0#
0/
0^
#260
1#
1/
1^
b000 v
b001 w
b010 x
b000 ~
b000 !!
b000 "!
b000 #!
b010 $!
b011 %!
b100 &!
b101 '!
#265
0#
0/
0^
#270
1#
1/
1^
b001 v
b010 w
b001 ~
b001 !!
b001 "!
b001 #!
#275
0#
0/
0^
#280
1#
1/
1^
b010 v
b011 w
b010 ~
b010 !!
b010 "!
b010 #!
#285
0#
0/
0^
#290
1#
1/
1^
b011 v
b100 w
b011 ~
b011 !!
b011 "!
b011 #!
#295
0#
0/
0^
#300
1#
1/
1^
b100 v
b101 w
b100 ~
b100 !!
b100 "!
b100 #!
#305
0#
0/
0^
#310
1#
1/
1^
b101 v
b110 w
b101 ~
b101 !!
b101 "!
b101 #!
#315
0#
0/
0^
#320
1#
1/
1^
b0010 m
b011 q
b101 u
b110 v
b000 w
b000 y
b110 ~
b110 !!
b110 "!
b110 #!
#325
0#
0/
0^
#330
1#
1/
1^
b0010 l
b011 p
b101 t
b000 v
b001 w
b000 x
b000 ~
b001 !!
b010 "!
b011 #!
b000 $!
b000 %!
b000 &!
b000 '!
#335
0#
0/
0^
#340
1#
1/
1^
b001 v
b010 w
b001 ~
b010 !!
b011 "!
b100 #!
#345
0#
0/
0^
#350
1#
1/
1^
b010 v
b011 w
b010 ~
b011 !!
b100 "!
b101 #!
#355
0#
0/
0^
#360
1#
1/
1^
b011 v
b000 w
b001 y
b011 ~
b100 !!
b101 "!
b110 #!
#365
0#
0/
0^
#370
1#
1/
1^
b000 v
b001 w
b001 x
b000 ~
b001 !!
b010 "!
b011 #!
b001 $!
b001 %!
b001 &!
b001 '!
#375
0#
0/
0^
#380
1#
1/
1^
b001 v
b010 w
b001 ~
b010 !!
b011 "!
b100 #!
#385
0#
0/
0^
#390
1#
1/
1^
b010 v
b011 w
b010 ~
b011 !!
b100 "!
b101 #!
#395
0#
0/
0^
#400
1#
1/
1^
b011 v
b000 w
b010 y
b011 ~
b100 !!
b101 "!
b110 #!
#405
0#
0/
0^
#410
1#
1/
1^
b000 v
b001 w
b010 x
b000 ~
b001 !!
b010 "!
b011 #!
b010 $!
b010 %!
b010 &!
b010 '!
#415
0#
0/
0^
#420
1#
1/
1^
b001 v
b010 w
b001 ~
b010 !!
b011 "!
b100 #!
#425
0#
0/
0^
#430
1#
1/
1^
b010 v
b011 w
b010 ~
b011 !!
b100 "!
b101 #!
#435
0#
0/
0^
#440
1#
1/
1^
b011 v
b000 w
b011 y
b011 ~
b100 !!
b101 "!
b110 #!
#445
0#
0/
0^
#450
1#
1/
1^
b000 v
b001 w
b011 x
b000 ~
b001 !!
b010 "!
b011 #!
b011 $!
b011 %!
b011 &!
b011 '!
#455
0#
0/
0^
#460
1#
1/
1^
b001 v
b010 w
b001 ~
b010 !!
b011 "!
b100 #!
#465
0#
0/
0^
#470
1#
1/
1^
b010 v
b011 w
b010 ~
b011 !!
b100 "!
b101 #!
#475
0#
0/
0^
#480
1#
1/
1^
b011 v
b000 w
b100 y
b011 ~
b100 !!
b101 "!
b110 #!
#485
0#
0/
0^
#490
1#
1/
1^
b000 v
b001 w
b100 x
b000 ~
b001 !!
b010 "!
b011 #!
b100 $!
b100 %!
b100 &!
b100 '!
#495
0#
0/
0^
#500
1#
1/
1^
b001 v
b010 w
b001 ~
b010 !!
b011 "!
b100 #!
#505
0#
0/
0^
#510
1#
1/
1^
b010 v
b011 w
b010 ~
b011 !!
b100 "!
b101 #!
#515
0#
0/
0^
#520
1#
1/
1^
b011 v
b000 w
b101 y
b011 ~
b100 !!
b101 "!
b110 #!
#525
0#
0/
0^
#530
1#
1/
1^
b000 v
b001 w
b101 x
b000 ~
b001 !!
b010 "!
b011 #!
b101 $!
b101 %!
b101 &!
b101 '!
#535
0#
0/
0^
#540
1#
1/
1^
b001 v
b010 w
b001 ~
b010 !!
b011 "!
b100 #!
#545
0#
0/
0^
#550
1#
1/
1^
b010 v
b011 w
b010 ~
b011 !!
b100 "!
b101 #!
#555
0#
0/
0^
#560
1#
1/
1^
b0011 m
b011 s
b011 v
b000 w
b011 y
b011 ~
b100 !!
b101 "!
b110 #!
#565
0#
0/
0^
#570
1#
1/
1^
b0011 l
b011 r
b000 v
b001 w
b011 x
b000 ~
b001 !!
b010 "!
b011 #!
b011 $!
b010 %!
b001 &!
b000 '!
#575
0#
0/
0^
#580
1#
1/
1^
b001 v
b010 w
b001 ~
b010 !!
b011 "!
b100 #!
#585
0#
0/
0^
#590
1#
1/
1^
b010 v
b011 w
b010 ~
b011 !!
b100 "!
b101 #!
#595
0#
0/
0^
#600
1#
1/
1^
b011 v
b000 w
b100 y
b011 ~
b100 !!
b101 "!
b110 #!
#605
0#
0/
0^
#610
1#
1/
1^
b000 v
b001 w
b100 x
b000 ~
b001 !!
b010 "!
b011 #!
b100 $!
b011 %!
b010 &!
b001 '!
#615
0#
0/
0^
#620
1#
1/
1^
b001 v
b010 w
b001 ~
b010 !!
b011 "!
b100 #!
#625
0#
0/
0^
#630
1#
1/
1^
b010 v
b011 w
b010 ~
b011 !!
b100 "!
b101 #!
#635
0#
0/
0^
#640
1#
1/
1^
b011 v
b000 w
b101 y
b011 ~
b100 !!
b101 "!
b110 #!
#645
0#
0/
0^
#650
1#
1/
1^
b000 v
b001 w
b101 x
b000 ~
b001 !!
b010 "!
b011 #!
b101 $!
b100 %!
b011 &!
b010 '!
#655
0#
0/
0^
#660
1#
1/
1^
b001 v
b010 w
b001 ~
b010 !!
b011 "!
b100 #!
#665
0#
0/
0^
#670
1#
1/
1^
b010 v
b011 w
b010 ~
b011 !!
b100 "!
b101 #!
#675
0#
0/
0^
#680
1#
1/
1^
b0100 m
b000 s
b010 u
b011 v
b000 w
b000 y
b011 ~
b100 !!
b101 "!
b110 #!
#685
0#
0/
0^
#690
1#
1/
1^
b0100 l
b000 r
b010 t
b000 v
b001 w
b000 x
b000 ~
b001 !!
b010 "!
b011 #!
b000 $!
b001 %!
b010 &!
b011 '!
#695
0#
0/
0^
#700
1#
1/
1^
b001 v
b010 w
b001 ~
b010 !!
b011 "!
b100 #!
#705
0#
0/
0^
#710
1#
1/
1^
b010 v
b011 w
b010 ~
b011 !!
b100 "!
b101 #!
#715
0#
0/
0^
#720
1#
1/
1^
b011 v
b000 w
b001 y
b011 ~
b100 !!
b101 "!
b110 #!
#725
0#
0/
0^
#730
1#
1/
1^
b000 v
b001 w
b001 x
b000 ~
b001 !!
b010 "!
b011 #!
b001 $!
b010 %!
b011 &!
b100 '!
#735
0#
0/
0^
#740
1#
1/
1^
b001 v
b010 w
b001 ~
b010 !!
b011 "!
b100 #!
#745
0#
0/
0^
#750
1#
1/
1^
b010 v
b011 w
b010 ~
b011 !!
b100 "!
b101 #!
#755
0#
0/
0^
#760
1#
1/
1^
b011 v
b000 w
b010 y
b011 ~
b100 !!
b101 "!
b110 #!
#765
0#
0/
0^
#770
1#
1/
1^
b000 v
b001 w
b010 x
b000 ~
b001 !!
b010 "!
b011 #!
b010 $!
b011 %!
b100 &!
b101 '!
#775
0#
0/
0^
#780
1#
1/
1^
b001 v
b010 w
b001 ~
b010 !!
b011 "!
b100 #!
#785
0#
0/
0^
#790
1#
1/
1^
b010 v
b011 w
b010 ~
b011 !!
b100 "!
b101 #!
#795
0#
0/
0^
#800
1#
1/
1^
1j
b0101 m
b011 v
b000 w
b011 y
b011 ~
b100 !!
b101 "!
b110 #!
#805
0#
0/
0^
#810
1#
1/
1<
b0100 B
0U
1V
1[
1^
1g
1i
0j
b0101 l
b0000 m
b000 v
b011 x
1{
0}
b000 ~
b000 !!
b000 "!
b000 #!
b000 $!
b000 %!
b000 &!
b000 '!
#815
0#
0/
0^
#820
1#
1*
1/
16
1;
0<
b0100 A
b0000 B
1Q
0T
0V
1Y
0[
1^
1d
0f
0g
b0000 l
0{
#825
0#
0/
0^
#830
1#
1%
0*
1/
11
06
b0000 A
0Y
1^
#835
0#
0)
0/
05
0^
#840
1#
1/
1^
#845
0#
0/
0^
#850
1#
1/
1^
#855
0#
1&
1'
b001 (
0/
12
13
b001 4
0;
b0001 B
b000000100000000000000000000000000000000010 G
b000000000000000000000000000000000000000010 I
1L
b001 N
b000 P
1X
0^
#860
1#
0%
1/
01
b0001 A
b000000100000000000000000000000000000000010 C
b000000000000000000000000000000000000000010 E
b000000100000000000000000000000000100000000 G
b000000000000000000000000000000000100000000 I
1K
b001 M
b000 O
b001 P
0X
b0000010 \
1^
b000000100000000000000000000000000000000010 `
b000000000000000000000000000000000000000010 b
#865
0#
0&
1)
0/
02
15
0^
#870
1#
1/
b000000100000000000000000000000000100000000 C
b000000000000000000000000000000000100000000 E
b000000100000000000000000001000000000000000 G
b000000000000000000000000001000000000000000 I
b001 O
b010 P
b0000000 \
1^
b000000100000000000000000000000000100000000 `
b000000000000000000000000000000000100000000 b
#875
0#
0/
0^
#880
1#
1/
b000000100000000000000000001000000000000000 C
b000000000000000000000000001000000000000000 E
b000000100000000000010000000000000000000000 G
b000000000000000000010000000000000000000000 I
b010 O
b011 P
1^
b000000100000000000000000001000000000000000 `
b000000000000000000000000001000000000000000 b
#885
0#
0/
0^
#890
1#
1/
b000000100000000000010000000000000000000000 C
b000000000000000000010000000000000000000000 E
b000000100000100000000000000000000000000000 G
b000000000000100000000000000000000000000000 I
b011 O
b100 P
1^
b000000100000000000010000000000000000000000 `
b000000000000000000010000000000000000000000 b
#895
0#
0/
0^
