dlab_konane/design_src/konane.v
module konane (
    input clk,
    input rst_n,

    output reg op_ready,
    input op_valid,
    input signed [4:0] op_i,
    input signed [4:0] op_j,

    input re_ready,
    output reg re_valid,
    output reg re_is_finished,
    output reg re_next_player_id,
    output reg re_player_can_giveup,
    output reg [35:0] re_selectable
);

localparam BLACK = 0, WHITE = 1;

localparam NORTH = 0,
           EAST  = 1,
           SOUTH = 2,
           WEST  = 3;

localparam S_CH_OP       = 0,
           S_CH_RE       = 1,
           S_JCH_OP      = 2,
           S_J_MV        = 3,
           S_J_UPDATE    = 4,
           S_J_JUDGE     = 5,
           S_J_STILL_RE  = 6,
           S_J_NOMOVE_RE = 7,
           S_JN_OP       = 8;


// It can be observed that black cells are restricted to holding only black pieces, and white cells only white pieces.
// We created two bit map:
//     BLACK_POSSIBLE: 6*6 bit map, "if and only if" position i, j is a restricted-to-holding black cell, the BLACK_POSSIBLE[6*i+j] will be 1.
//     WHITE_POSSIBLE: 6*6 bit map, "if and only if" position i, j is a restricted-to-holding white cell, the WHITE_POSSIBLE[6*i+j] will be 1.
localparam BLACK_POSSIBLE = {
    3{
        {3{2'b10}}, {3{2'b01}}
    }
};

localparam WHITE_POSSIBLE = {
    3{
        /* what is the const here */
    }
};

reg op_ready_nxt;
reg re_valid_nxt;
reg re_is_finished_nxt;
reg re_next_player_id_nxt;


reg [3:0] S, S_nxt;

reg player_id, player_id_nxt;
reg [4:0] ci, ci_nxt;
reg [4:0] cj, cj_nxt;
reg [4:0] ji, ji_nxt;
reg [4:0] jj, jj_nxt;
reg [4:0] ui, ui_nxt;
reg [4:0] uj, uj_nxt;
reg [1:0] dir, dir_nxt;

reg [35:0] occupied /* verilator public */;
reg [35:0] occupied_nxt;

reg [35:0] N_canjump, N_canjump_nxt;
reg [35:0] E_canjump, E_canjump_nxt;
reg [35:0] S_canjump, S_canjump_nxt;
reg [35:0] W_canjump, W_canjump_nxt;

reg op_fire, re_fire;

wire [35:0] su_o_update;

reg [35:0] black_all /* verilator public */;
reg [35:0] white_all /* verilator public */;
reg [35:0] black_movable_all;
reg [35:0] white_movable_all;
reg [35:0] N_cij_can_jumpto;
reg [35:0] E_cij_can_jumpto;
reg [35:0] S_cij_can_jumpto;
reg [35:0] W_cij_can_jumpto;
reg [35:0] all_cij_can_jumpto;
reg black_no_move, white_no_move;

reg [6:0] cij2idx;
reg [6:0] jij2idx;
reg [6:0] uij2idx;
reg [6:0] op_ij2idx;
reg signed [4:0] i_dist, j_dist;

reg [35:0] selectable;

integer i, j;

always @(*) begin
    op_fire = op_ready & op_valid;
    re_fire = re_ready & re_valid;

    cij2idx = ci * 6 + cj;
    jij2idx = ji * 6 + jj;
    uij2idx = ui * 6 + uj;
    op_ij2idx = op_i * 6 + op_j;

    black_all = BLACK_POSSIBLE & occupied;
    white_all = WHITE_POSSIBLE & occupied;
    black_movable_all = black_all & (N_canjump | E_canjump | S_canjump | W_canjump);
    white_movable_all = white_all & (N_canjump | E_canjump | S_canjump | W_canjump);
    for (i = 0; i < 6; i = i + 1) begin
        for (j = 0; j < 6; j = j + 1) begin
            N_cij_can_jumpto[i * 6 + j] = ((ci > 1) && ((ci - 2) == i) && (cj == j) && N_canjump[cij2idx]);
            E_cij_can_jumpto[i * 6 + j] = ((cj < 4) && ((cj + 2) == j) && (ci == i) && E_canjump[cij2idx]);
            S_cij_can_jumpto[i * 6 + j] = ((ci < 4) && ((ci + 2) == i) && (cj == j) && S_canjump[cij2idx]);
            W_cij_can_jumpto[i * 6 + j] = ((cj > 1) && ((cj - 2) == j) && (ci == i) && W_canjump[cij2idx]);
        end
    end
    all_cij_can_jumpto = N_cij_can_jumpto | E_cij_can_jumpto | S_cij_can_jumpto | W_cij_can_jumpto;

    black_no_move = ~|(black_all & (N_canjump | E_canjump | S_canjump | W_canjump));
    white_no_move = ~|(white_all & (N_canjump | E_canjump | S_canjump | W_canjump));

    i_dist = ji - ci;
    j_dist = jj - cj;

    op_ready_nxt = op_ready;
    re_valid_nxt = re_valid;
    re_is_finished_nxt = re_is_finished;
    re_next_player_id_nxt = re_next_player_id;

    S_nxt = S;

    player_id_nxt = player_id;
    ci_nxt = ci;
    cj_nxt = cj;
    ji_nxt = ji;
    jj_nxt = jj;
    ui_nxt = ui;
    uj_nxt = uj;
    dir_nxt = dir;

    occupied_nxt = occupied;
    N_canjump_nxt = N_canjump;
    E_canjump_nxt = E_canjump;
    S_canjump_nxt = S_canjump;
    W_canjump_nxt = W_canjump;

    case (S)
        S_CH_OP: begin
            if (op_fire) begin
                op_ready_nxt = 0;
                ci_nxt = op_i;
                cj_nxt = op_j;
                re_valid_nxt = 1;
                re_next_player_id_nxt = player_id;
                S_nxt = S_CH_RE;
            end
        end
        S_CH_RE: begin
            if (re_fire) begin
                op_ready_nxt = 1;
                re_valid_nxt = 0;
                re_next_player_id_nxt = 0;
                S_nxt = S_JCH_OP;
            end
        end
        S_JCH_OP: begin
            if (op_fire) begin
                op_ready_nxt = 0;
                if (occupied[op_ij2idx]) begin
                    ci_nxt = op_i;
                    cj_nxt = op_j;
                    re_valid_nxt = 1;
                    re_next_player_id_nxt = player_id;
                    S_nxt = S_CH_RE;
                end
                else begin
                    ji_nxt = op_i;
                    jj_nxt = op_j;
                    S_nxt = S_J_MV;
                end
            end
        end
        S_J_MV: begin
            occupied_nxt[jij2idx] = 1;
            occupied_nxt[cij2idx] = 0;
            occupied_nxt[($signed(ci) + i_dist/2) * 6 + ($signed(cj) + j_dist/2)] = 0;
            if (ji < ci) begin
                dir_nxt = NORTH;
            end
            else if (jj > cj) begin
                dir_nxt = EAST;
            end
            else if (ji > ci) begin
                dir_nxt = SOUTH;
            end
            else if (jj < cj) begin
                dir_nxt = WEST;
            end
            ui_nxt = 0;
            uj_nxt = 0;
            S_nxt = S_J_UPDATE;
        end
        S_J_UPDATE: begin
            N_canjump_nxt[uij2idx] = (ui > 1) && (~occupied[(ui - 2) * 6 + (uj    )]) && (occupied[(ui - 1) * 6 + (uj    )]) && (occupied[uij2idx]);
            E_canjump_nxt[uij2idx] = (uj < 4) && (~occupied[(ui    ) * 6 + (uj + 2)]) && (occupied[(ui    ) * 6 + (uj + 1)]) && (occupied[uij2idx]);
            S_canjump_nxt[uij2idx] = (ui < 4) && (~occupied[(ui + 2) * 6 + (uj    )]) && (occupied[(ui + 1) * 6 + (uj    )]) && (occupied[uij2idx]);
            W_canjump_nxt[uij2idx] = (uj > 1) && (~occupied[(ui    ) * 6 + (uj - 2)]) && (occupied[(ui    ) * 6 + (uj - 1)]) && (occupied[uij2idx]);
            // The ui, uj indicate the position testing now. In this state, the ui, uj will go through all position

            // uj needs to count 0 to 5 again and again, increases by 1 or wrap to zreo each cycle.
            uj_nxt = (uj == 5) ? /**/ : /**/ ;
            // ui needs to count 0 to 5, but only increases by 1 at uj == 5, holds the same value when uj is still running in the same row.
            ui_nxt = (uj == 5) ? /**/ : /**/ ;

            if (ui == 5 && uj == 5) begin
                S_nxt = S_J_JUDGE;
            end
            else begin
                S_nxt = S_J_UPDATE;
            end
        end
        S_J_JUDGE: begin
            if (
                ((dir == NORTH) && (N_canjump[jij2idx])) ||
                ((dir == EAST ) && (E_canjump[jij2idx])) ||
                ((dir == SOUTH) && (S_canjump[jij2idx])) ||
                ((dir == WEST ) && (W_canjump[jij2idx]))
            ) begin
                re_valid_nxt = 1;
                ci_nxt = ji;
                cj_nxt = jj;
                re_is_finished_nxt = (player_id == WHITE && black_no_move) || (player_id == BLACK && white_no_move);
                re_next_player_id_nxt = player_id;
                S_nxt = S_J_STILL_RE;
            end
            else begin
                re_valid_nxt = 1;
                ci_nxt = 0;
                cj_nxt = 0;
                re_is_finished_nxt = (player_id == WHITE && black_no_move) || (player_id == BLACK && white_no_move);
                re_next_player_id_nxt = ~player_id;
                S_nxt = S_J_NOMOVE_RE;
            end
        end
        S_J_NOMOVE_RE: begin
            if (re_fire) begin
                re_valid_nxt = 0;
                op_ready_nxt = 1;
                if (re_is_finished) begin
                    S_nxt = S_CH_OP;

                    player_id_nxt = BLACK;
                    ci_nxt = 0;
                    cj_nxt = 0;
                    ji_nxt = 0;
                    jj_nxt = 0;
                    ui_nxt = 0;
                    uj_nxt = 0;
                    dir_nxt = 0;

                    for (i = 0; i < 36; i = i + 1) begin
                        occupied_nxt[i]  = (i == 14 || i == 15) ? 0 : 1;
                        N_canjump_nxt[i] = (i == 26 || i == 27) ? 1 : 0;
                        E_canjump_nxt[i] = (i == 12           ) ? 1 : 0;
                        S_canjump_nxt[i] = (i ==  2 || i ==  3) ? 1 : 0;
                        W_canjump_nxt[i] = (i == 17           ) ? 1 : 0;
                    end
                end
                player_id_nxt = ~player_id;
                S_nxt = S_CH_OP;
            end
        end
        S_J_STILL_RE: begin
            if (re_fire) begin
                re_valid_nxt = 0;
                op_ready_nxt = 1;
                if (re_is_finished) begin
                    S_nxt = S_CH_OP;

                    player_id_nxt = BLACK;
                    ci_nxt = 0;
                    cj_nxt = 0;
                    ji_nxt = 0;
                    jj_nxt = 0;
                    ui_nxt = 0;
                    uj_nxt = 0;
                    dir_nxt = 0;

                    for (i = 0; i < 36; i = i + 1) begin
                        occupied_nxt[i]  = (i == 14 || i == 15) ? 0 : 1;
                        N_canjump_nxt[i] = (i == 26 || i == 27) ? 1 : 0;
                        E_canjump_nxt[i] = (i == 12           ) ? 1 : 0;
                        S_canjump_nxt[i] = (i ==  2 || i ==  3) ? 1 : 0;
                        W_canjump_nxt[i] = (i == 17           ) ? 1 : 0;
                    end
                end
                else begin
                    S_nxt = S_JN_OP;
                end
            end
        end
        S_JN_OP: begin
            if (op_fire) begin
                op_ready_nxt = 0;
                if (op_i < 0 || op_j < 0) begin
                    re_valid_nxt = 1;
                    ci_nxt = 0;
                    cj_nxt = 0;
                    re_is_finished_nxt = (player_id == WHITE && black_no_move) || (player_id == BLACK && white_no_move);
                    re_next_player_id_nxt = ~player_id;
                    S_nxt = S_J_NOMOVE_RE;
                end
                else begin
                    ji_nxt = op_i;
                    jj_nxt = op_j;
                    S_nxt = S_J_MV;
                end
            end
        end
        default: begin
        end
    endcase
end

always @(posedge clk, negedge rst_n) begin
    if (~rst_n) begin
        op_ready <= 1;
        re_valid <= 0;
        re_is_finished <= 0;
        re_next_player_id <= 0;

        S <= S_CH_OP;

        player_id <= BLACK;
        ci <= 0;
        cj <= 0;
        ji <= 0;
        jj <= 0;
        ui <= 0;
        uj <= 0;
        dir <= 0;

        for (i = 0; i < 36; i = i + 1) begin
            occupied[i]  <= (i == 14 || i == 15) ? 0 : 1;
            N_canjump[i] <= (i == 26 || i == 27) ? 1 : 0;
            E_canjump[i] <= (i == 12           ) ? 1 : 0;
            S_canjump[i] <= (i ==  2 || i ==  3) ? 1 : 0;
            W_canjump[i] <= (i == 17           ) ? 1 : 0;
        end
        
    end
    else begin
        op_ready <= op_ready_nxt;
        re_valid <= re_valid_nxt;
        re_is_finished <= re_is_finished_nxt;
        re_next_player_id <= re_next_player_id_nxt;

        S <= S_nxt;

        player_id <= player_id_nxt;
        ci <= ci_nxt;
        cj <= cj_nxt;
        ji <= ji_nxt;
        jj <= jj_nxt;
        ui <= ui_nxt;
        uj <= uj_nxt;
        dir <= dir_nxt;

        occupied <= occupied_nxt;
        N_canjump <= N_canjump_nxt;
        E_canjump <= E_canjump_nxt;
        S_canjump <= S_canjump_nxt;
        W_canjump <= W_canjump_nxt;
    end
end

always @(*) begin
    case (S)
        S_CH_RE: begin
            re_selectable = all_cij_can_jumpto | ((player_id == BLACK ? black_movable_all : white_movable_all));
            re_player_can_giveup = 0;
        end
        S_J_NOMOVE_RE: begin
            re_selectable = (re_next_player_id == BLACK) ? black_movable_all : white_movable_all;
            re_player_can_giveup = 0;
        end
        S_J_STILL_RE: begin
            if (re_is_finished) begin
                re_selectable = 36'b000000000100000000000001000000000100;
                re_player_can_giveup = 0;
            end
            else begin
                case (dir)
                    NORTH  : re_selectable = N_cij_can_jumpto;
                    EAST   : re_selectable = E_cij_can_jumpto;
                    SOUTH  : re_selectable = S_cij_can_jumpto;
                    WEST   : re_selectable = W_cij_can_jumpto;
                    default: re_selectable = 0;
                endcase
                re_player_can_giveup = 1;
            end
        end
        default: begin
            re_selectable = 0;
            re_player_can_giveup = 0;
        end
    endcase
end

endmodule

dlab_konane/golden/blackwin.vcd
$version Generated by VerilatedVcd $end
$timescale 1ps $end
 $scope module TOP $end
  $scope module konane $end
   $var wire 1 0 clk $end
   $var wire 1 1 rst_n $end
   $var wire 1 2 op_ready $end
   $var wire 1 3 op_valid $end
   $var wire 5 4 op_i [4:0] $end
   $var wire 5 5 op_j [4:0] $end
   $var wire 1 6 re_ready $end
   $var wire 1 7 re_valid $end
   $var wire 1 8 re_is_finished $end
   $var wire 1 9 re_next_player_id $end
   $var wire 1 : re_player_can_giveup $end
   $var wire 36 ; re_selectable [35:0] $end
   $var wire 32 +! BLACK [31:0] $end
   $var wire 32 ,! WHITE [31:0] $end
   $var wire 32 +! NORTH [31:0] $end
   $var wire 32 ,! EAST [31:0] $end
   $var wire 32 -! SOUTH [31:0] $end
   $var wire 32 .! WEST [31:0] $end
   $var wire 32 +! S_CH_OP [31:0] $end
   $var wire 32 ,! S_CH_RE [31:0] $end
   $var wire 32 -! S_JCH_OP [31:0] $end
   $var wire 32 .! S_J_MV [31:0] $end
   $var wire 32 /! S_J_UPDATE [31:0] $end
   $var wire 32 0! S_J_JUDGE [31:0] $end
   $var wire 32 1! S_J_STILL_RE [31:0] $end
   $var wire 32 2! S_J_NOMOVE_RE [31:0] $end
   $var wire 32 3! S_JN_OP [31:0] $end
   $var wire 36 4! BLACK_POSSIBLE [35:0] $end
   $var wire 36 6! WHITE_POSSIBLE [35:0] $end
   $var wire 1 = op_ready_nxt $end
   $var wire 1 > re_valid_nxt $end
   $var wire 1 ? re_is_finished_nxt $end
   $var wire 1 @ re_next_player_id_nxt $end
   $var wire 4 A S [3:0] $end
   $var wire 4 B S_nxt [3:0] $end
   $var wire 1 C player_id $end
   $var wire 1 D player_id_nxt $end
   $var wire 5 E ci [4:0] $end
   $var wire 5 F ci_nxt [4:0] $end
   $var wire 5 G cj [4:0] $end
   $var wire 5 H cj_nxt [4:0] $end
   $var wire 5 I ji [4:0] $end
   $var wire 5 J ji_nxt [4:0] $end
   $var wire 5 K jj [4:0] $end
   $var wire 5 L jj_nxt [4:0] $end
   $var wire 5 M ui [4:0] $end
   $var wire 5 N ui_nxt [4:0] $end
   $var wire 5 O uj [4:0] $end
   $var wire 5 P uj_nxt [4:0] $end
   $var wire 2 Q dir [1:0] $end
   $var wire 2 R dir_nxt [1:0] $end
   $var wire 36 S occupied [35:0] $end
   $var wire 36 U occupied_nxt [35:0] $end
   $var wire 36 W N_canjump [35:0] $end
   $var wire 36 Y N_canjump_nxt [35:0] $end
   $var wire 36 [ E_canjump [35:0] $end
   $var wire 36 ] E_canjump_nxt [35:0] $end
   $var wire 36 _ S_canjump [35:0] $end
   $var wire 36 a S_canjump_nxt [35:0] $end
   $var wire 36 c W_canjump [35:0] $end
   $var wire 36 e W_canjump_nxt [35:0] $end
   $var wire 1 g op_fire $end
   $var wire 1 h re_fire $end
   $var wire 36 i su_o_update [35:0] $end
   $var wire 36 k black_all [35:0] $end
   $var wire 36 m white_all [35:0] $end
   $var wire 36 o black_movable_all [35:0] $end
   $var wire 36 q white_movable_all [35:0] $end
   $var wire 36 s N_cij_can_jumpto [35:0] $end
   $var wire 36 u E_cij_can_jumpto [35:0] $end
   $var wire 36 w S_cij_can_jumpto [35:0] $end
   $var wire 36 y W_cij_can_jumpto [35:0] $end
   $var wire 36 { all_cij_can_jumpto [35:0] $end
   $var wire 1 } black_no_move $end
   $var wire 1 ~ white_no_move $end
   $var wire 7 !! cij2idx [6:0] $end
   $var wire 7 "! jij2idx [6:0] $end
   $var wire 7 #! uij2idx [6:0] $end
   $var wire 7 $! op_ij2idx [6:0] $end
   $var wire 5 %! i_dist [4:0] $end
   $var wire 5 &! j_dist [4:0] $end
   $var wire 36 '! selectable [35:0] $end
   $var wire 32 )! i [31:0] $end
   $var wire 32 *! j [31:0] $end
  $upscope $end
  $var wire 1 # clk $end
  $var wire 1 $ rst_n $end
  $var wire 1 % op_ready $end
  $var wire 1 & op_valid $end
  $var wire 5 ' op_i [4:0] $end
  $var wire 5 ( op_j [4:0] $end
  $var wire 1 ) re_ready $end
  $var wire 1 * re_valid $end
  $var wire 1 + re_is_finished $end
  $var wire 1 , re_next_player_id $end
  $var wire 1 - re_player_can_giveup $end
  $var wire 36 . re_selectable [35:0] $end
 $upscope $end
$enddefinitions $end


#5
0#
0$
0%
0&
b00000 '
b00000 (
0)
0*
0+
0,
0-
b000000000000000000000000000000000000 .
00
01
02
03
b00000 4
b00000 5
06
07
08
09
0:
b000000000000000000000000000000000000 ;
0=
0>
0?
0@
b0000 A
b0000 B
0C
0D
b00000 E
b00000 F
b00000 G
b00000 H
b00000 I
b00000 J
b00000 K
b00000 L
b00000 M
b00000 N
b00000 O
b00000 P
b00 Q
b00 R
b000000000000000000000000000000000000 S
b000000000000000000000000000000000000 U
b000000000000000000000000000000000000 W
b000000000000000000000000000000000000 Y
b000000000000000000000000000000000000 [
b000000000000000000000000000000000000 ]
b000000000000000000000000000000000000 _
b000000000000000000000000000000000000 a
b000000000000000000000000000000000000 c
b000000000000000000000000000000000000 e
0g
0h
b000000000000000000000000000000000000 i
b000000000000000000000000000000000000 k
b000000000000000000000000000000000000 m
b000000000000000000000000000000000000 o
b000000000000000000000000000000000000 q
b000000000000000000000000000000000000 s
b000000000000000000000000000000000000 u
b000000000000000000000000000000000000 w
b000000000000000000000000000000000000 y
b000000000000000000000000000000000000 {
1}
1~
b0000000 !!
b0000000 "!
b0000000 #!
b0000000 $!
b00000 %!
b00000 &!
b000000000000000000000000000000000000 '!
b00000000000000000000000000000110 )!
b00000000000000000000000000000110 *!
b00000000000000000000000000000000 +!
b00000000000000000000000000000001 ,!
b00000000000000000000000000000010 -!
b00000000000000000000000000000011 .!
b00000000000000000000000000000100 /!
b00000000000000000000000000000101 0!
b00000000000000000000000000000110 1!
b00000000000000000000000000000111 2!
b00000000000000000000000000001000 3!
b101010010101101010010101101010010101 4!
b010101101010010101101010010101101010 6!
#10
1#
1%
10
12
1=
b111111111111111111110011111111111111 S
b111111111111111111110011111111111111 U
b000000001100000000000000000000000000 W
b000000001100000000000000000000000000 Y
b000000000000000000000001000000000000 [
b000000000000000000000001000000000000 ]
b000000000000000000000000000000001100 _
b000000000000000000000000000000001100 a
b000000000000000000100000000000000000 c
b000000000000000000100000000000000000 e
b101010010101101010010001101010010101 k
b010101101010010101100010010101101010 m
b000000000100000000000001000000000100 o
b000000001000000000100000000000001000 q
0}
0~
#15
0#
00
#20
1#
10
#25
0#
1$
00
11
#30
1#
10
#35
0#
00
#40
1#
10
#45
0#
1&
b00100 '
b00010 (
00
13
b00100 4
b00010 5
0=
1>
b0001 B
b00100 F
b00010 H
1g
b0011010 $!
#50
1#
0%
1*
b000000000100000000000101000000000100 .
10
02
17
b000000000100000000000101000000000100 ;
b0001 A
b00100 E
b00010 G
0g
b000000000000000000000100000000000000 s
b000000000000000000000100000000000000 {
b0011010 !!
b11100 %!
b11110 &!
#55
0#
0&
1)
00
03
16
1=
0>
b0010 B
1h
#60
1#
1%
0*
b000000000000000000000000000000000000 .
10
12
07
b000000000000000000000000000000000000 ;
b0010 A
0h
#65
0#
0)
00
06
#70
1#
10
#75
0#
00
#80
1#
10
#85
0#
1&
b00010 '
00
13
b00010 4
0=
b0011 B
b00010 J
b00010 L
1g
b0001110 $!
#90
1#
0%
10
02
b0011 A
b0100 B
b00010 I
b00010 K
b111111111011111011110111111111111111 U
0g
b0001110 "!
b11110 %!
b00000 &!
#95
0#
0&
1)
00
03
16
#100
1#
10
b0100 A
b00001 P
b111111111011111011110111111111111111 S
b101010010001101010010101101010010101 k
b010101101010010001100010010101101010 m
b000000000000000000000001000000000100 o
#105
0#
00
#110
1#
10
b00001 O
b00010 P
b0000001 #!
#115
0#
00
#120
1#
10
b00010 O
b00011 P
b000000000000000000000000000000001000 a
b0000010 #!
#125
0#
00
#130
1#
10
b00011 O
b00100 P
b000000000000000000000000000000001000 _
b000000000000000000000001000000000000 o
b0000011 #!
#135
0#
00
#140
1#
10
b00100 O
b00101 P
b0000100 #!
#145
0#
00
#150
1#
10
b00001 N
b00101 O
b00000 P
b0000101 #!
#155
0#
00
#160
1#
10
b00001 M
b00000 O
b00001 P
b0000110 #!
#165
0#
00
#170
1#
10
b00001 O
b00010 P
b0000111 #!
#175
0#
00
#180
1#
10
b00010 O
b00011 P
b000000000000000000000000000100001000 a
b0001000 #!
#185
0#
00
#190
1#
10
b00011 O
b00100 P
b000000000000000000000000000100001000 _
b000000001000000000100000000100001000 q
b0001001 #!
#195
0#
00
#200
1#
10
b00100 O
b00101 P
b0001010 #!
#205
0#
00
#210
1#
10
b00010 N
b00101 O
b00000 P
b0001011 #!
#215
0#
00
#220
1#
10
b00010 M
b00000 O
b00001 P
b000000000000000000000000000000000000 ]
b0001100 #!
#225
0#
00
#230
1#
10
b00001 O
b00010 P
b000000000000000000000000000000000000 [
b000000000000000000000010000000000000 ]
b000000000000000000000000000000000000 o
1}
b0001101 #!
#235
0#
00
#240
1#
10
b00010 O
b00011 P
b000000000000000000000010000000000000 [
b000000001000000000100010000100001000 q
b0001110 #!
#245
0#
00
#250
1#
10
b00011 O
b00100 P
b0001111 #!
#255
0#
00
#260
1#
10
b00100 O
b00101 P
b0010000 #!
#265
0#
00
#270
1#
10
b00011 N
b00101 O
b00000 P
b0010001 #!
#275
0#
00
#280
1#
10
b00011 M
b00000 O
b00001 P
b000000000000000001000010000000000000 ]
b0010010 #!
#285
0#
00
#290
1#
10
b00001 O
b00010 P
b000000000000000001000010000000000000 [
b000000001000000001100010000100001000 q
b0010011 #!
#295
0#
00
#300
1#
10
b00010 O
b00011 P
b0010100 #!
#305
0#
00
#310
1#
10
b00011 O
b00100 P
b0010101 #!
#315
0#
00
#320
1#
10
b00100 O
b00101 P
b000000000000010000100000000000000000 e
b0010110 #!
#325
0#
00
#330
1#
10
b00100 N
b00101 O
b00000 P
b000000000000010000100000000000000000 c
b000000001000010001100010000100001000 q
b0010111 #!
#335
0#
00
#340
1#
10
b00100 M
b00000 O
b00001 P
b000000000001000001000010000000000000 ]
b0011000 #!
#345
0#
00
#350
1#
10
b00001 O
b00010 P
b000000000001000001000010000000000000 [
b000000000001000000000000000000000000 o
0}
b0011001 #!
#355
0#
00
#360
1#
10
b00010 O
b00011 P
b000000001000000000000000000000000000 Y
b0011010 #!
#365
0#
00
#370
1#
10
b00011 O
b00100 P
b000000001000000000000000000000000000 W
b000000000000000000000000000000000000 s
b000000000000000000000000000000000000 {
b0011011 #!
#375
0#
00
#380
1#
10
b00100 O
b00101 P
b000000010000010000100000000000000000 e
b0011100 #!
#385
0#
00
#390
1#
10
b00101 N
b00101 O
b00000 P
b000000010000010000100000000000000000 c
b000000010001000000000000000000000000 o
b0011101 #!
#395
0#
00
#400
1#
10
b00101 M
b00000 O
b00001 P
b0011110 #!
#405
0#
00
#410
1#
10
b00001 O
b00010 P
b0011111 #!
#415
0#
00
#420
1#
10
b00010 O
b00011 P
b0100000 #!
#425
0#
00
#430
1#
10
b00011 O
b00100 P
b0100001 #!
#435
0#
00
#440
1#
10
b00100 O
b00101 P
b0100010 #!
#445
0#
00
#450
1#
10
b0101 B
b00110 N
b00101 O
b00000 P
b0100011 #!
#455
0#
00
#460
1#
10
1>
1@
b0101 A
b0111 B
b00000 F
b00000 H
b00110 M
b00000 O
b0100100 #!
#465
0#
00
#470
1#
1*
1,
b000000001000010001100010000100001000 .
10
17
19
b000000001000010001100010000100001000 ;
1=
0>
b0111 A
b0000 B
1D
b00000 E
b00000 G
1h
b0000000 !!
b00010 %!
b00010 &!
#475
0#
00
#480
1#
1%
0*
b000000000000000000000000000000000000 .
10
12
07
b000000000000000000000000000000000000 ;
b0000 A
1C
0h
#485
0#
0)
00
06
#490
1#
10
#495
0#
00
#500
1#
10
#505
0#
1&
b00100 '
b00011 (
00
13
b00100 4
b00011 5
0=
1>
b0001 B
b00100 F
b00011 H
1g
b0011011 $!
#510
1#
0%
1*
b000000001000010001101010000100001000 .
10
02
17
b000000001000010001101010000100001000 ;
b0001 A
b00100 E
b00011 G
0g
b000000000000000000001000000000000000 s
b000000000000000000001000000000000000 {
b0011011 !!
b11110 %!
b11111 &!
#515
0#
0&
1)
00
03
16
1=
0>
0@
b0010 B
1h
#520
1#
1%
0*
0,
b000000000000000000000000000000000000 .
10
12
07
09
b000000000000000000000000000000000000 ;
b0010 A
0h
#525
0#
0)
00
06
#530
1#
10
#535
0#
00
#540
1#
10
#545
0#
1&
b00010 '
00
13
b00010 4
0=
b0011 B
b00011 L
1g
b0001111 $!
#550
1#
0%
10
02
b0011 A
b0100 B
b00011 K
b00000 N
b111111110011110011111111111111111111 U
0g
b0001111 "!
b00000 &!
#555
0#
0&
1)
00
03
16
#560
1#
10
b0100 A
b00000 M
b00001 P
b111111110011110011111111111111111111 S
b101010010001100010010101101010010101 k
b010101100010010001101010010101101010 m
b000000000000010001100010000100001000 q
b0000000 #!
#565
0#
00
#570
1#
10
b00001 O
b00010 P
b0000001 #!
#575
0#
00
#580
1#
10
b00010 O
b00011 P
b0000010 #!
#585
0#
00
#590
1#
10
b00011 O
b00100 P
b000000000000000000000000000100000000 a
b0000011 #!
#595
0#
00
#600
1#
10
b00100 O
b00101 P
b000000000000000000000000000100000000 _
b000000000000010001100010000100000000 q
b0000100 #!
#605
0#
00
#610
1#
10
b00001 N
b00101 O
b00000 P
b0000101 #!
#615
0#
00
#620
1#
10
b00001 M
b00000 O
b00001 P
b0000110 #!
#625
0#
00
#630
1#
10
b00001 O
b00010 P
b0000111 #!
#635
0#
00
#640
1#
10
b00010 O
b00011 P
b0001000 #!
#645
0#
00
#650
1#
10
b00011 O
b00100 P
b000000000000000000000000001100000000 a
b0001001 #!
#655
0#
00
#660
1#
10
b00100 O
b00101 P
b000000000000000000000000001100000000 _
b000000010001000000000000001000000000 o
b0001010 #!
#665
0#
00
#670
1#
10
b00010 N
b00101 O
b00000 P
b0001011 #!
#675
0#
00
#680
1#
10
b00010 M
b00000 O
b00001 P
b0001100 #!
#685
0#
00
#690
1#
10
b00001 O
b00010 P
b000000000001000001000000000000000000 ]
b0001101 #!
#695
0#
00
#700
1#
10
b00010 O
b00011 P
b000000000001000001000000000000000000 [
b000000000000010001100000000100000000 q
b0001110 #!
#705
0#
00
#710
1#
10
b00011 O
b00100 P
b0001111 #!
#715
0#
00
#720
1#
10
b00100 O
b00101 P
b0010000 #!
#725
0#
00
#730
1#
10
b00011 N
b00101 O
b00000 P
b000000010000010000000000000000000000 e
b0010001 #!
#735
0#
00
#740
1#
10
b00011 M
b00000 O
b00001 P
b000000010000010000000000000000000000 c
b000000000000010001000000000100000000 q
b0010010 #!
#745
0#
00
#750
1#
10
b00001 O
b00010 P
b0010011 #!
#755
0#
00
#760
1#
10
b00010 O
b00011 P
b0010100 #!
#765
0#
00
#770
1#
10
b00011 O
b00100 P
b0010101 #!
#775
0#
00
#780
1#
10
b00100 O
b00101 P
b000000010000000000000000000000000000 e
b0010110 #!
#785
0#
00
#790
1#
10
b00100 N
b00101 O
b00000 P
b000000010000000000000000000000000000 c
b000000010000100000000000000000000000 e
b000000000000000001000000000100000000 q
b0010111 #!
#795
0#
00
#800
1#
10
b00100 M
b00000 O
b00001 P
b000000010000100000000000000000000000 c
b000000010001100000000000001000000000 o
b0011000 #!
#805
0#
00
#810
1#
10
b00001 O
b00010 P
b0011001 #!
#815
0#
00
#820
1#
10
b00010 O
b00011 P
b0011010 #!
#825
0#
00
#830
1#
10
b00011 O
b00100 P
b000000000000000000000000000000000000 Y
b0011011 #!
#835
0#
00
#840
1#
10
b00100 O
b00101 P
b000000000000000000000000000000000000 W
b000000000000100000000000000000000000 e
b000000000000000000000000000000000000 s
b000000000000000000000000000000000000 {
b0011100 #!
#845
0#
00
#850
1#
10
b00101 N
b00101 O
b00000 P
b000000000000100000000000000000000000 c
b000000100000100000000000000000000000 e
b000000000001100000000000001000000000 o
b0011101 #!
#855
0#
00
#860
1#
10
b00101 M
b00000 O
b00001 P
b000000100000100000000000000000000000 c
b000000100000000001000000000100000000 q
b0011110 #!
#865
0#
00
#870
1#
10
b00001 O
b00010 P
b0011111 #!
#875
0#
00
#880
1#
10
b00010 O
b00011 P
b0100000 #!
#885
0#
00
#890
1#
10
b00011 O
b00100 P
b0100001 #!
#895
0#
00
#900
1#
10
b00100 O
b00101 P
b0100010 #!
#905
0#
00
#910
1#
10
b0101 B
b00110 N
b00101 O
b00000 P
b0100011 #!
#915
0#
00
#920
1#
10
1>
b0101 A
b0111 B
b00000 F
b00000 H
b00110 M
b00000 O
b0100100 #!
#925
0#
00
#930
1#
1*
b000000000001100000000000001000000000 .
10
17
b000000000001100000000000001000000000 ;
1=
0>
b0111 A
b0000 B
0D
b00000 E
b00000 G
1h
b0000000 !!
b00010 %!
b00011 &!
#935
0#
00
#940
1#
1%
0*
b000000000000000000000000000000000000 .
10
12
07
b000000000000000000000000000000000000 ;
b0000 A
0C
0h
#945
0#
0)
00
06
#950
1#
10
#955
0#
00
#960
1#
10
#965
0#
1&
b00100 '
b00000 (
00
13
b00100 4
b00000 5
0=
1>
b0001 B
b00100 F
1g
b0011000 $!
#970
1#
0%
1*
b000000000101100000000000001000000000 .
10
02
17
b000000000101100000000000001000000000 ;
b0001 A
b00100 E
0g
b000000000100000000000000000000000000 u
b000000000100000000000000000000000000 {
b0011000 !!
b11110 %!
