dlab_kalah/design_src/kalah.v
module kalah (
    input       clk,
    input       rst_n,
    output reg  op_ready,
    input       op_valid,
    input       op_player_id,
    input [2:0] op_pit_id,

    input       re_ready,
    output reg  re_valid,
    output reg  re_operr,
    output reg  re_next_player_id,
    output reg  re_is_finished,
    output reg [7:0] re_player0_score,
    output reg [7:0] re_player1_score
);

reg  op_ready_nxt;
reg  re_valid_nxt;
reg  re_operr_nxt;
reg  re_next_player_id_nxt;
reg  re_is_finished_nxt;
reg [7:0] re_player0_score_nxt;
reg [7:0] re_player1_score_nxt;

localparam S_WAIT_OP = 0,
           S_ERR_OP = 1,
           S_LAUNCH_SOW = 2,
           S_SOW = 3,
           S_LAUNCH_CAPTURE = 4,
           S_CAPTURE = 5,
           S_RE =  6;

localparam BOP_N   = 0,
           BOP_SOW = 1,
           BOP_CAP = 2,
           BOP_RST = 3;


wire       board_op_ready;
reg        board_op_valid    , board_op_valid_nxt;
reg        board_op_player_id, board_op_player_id_nxt;
reg  [2:0] board_op_pit_id   , board_op_pit_id_nxt;
reg  [1:0] board_op_op       , board_op_op_nxt;

reg        board_re_ready, board_re_ready_nxt;
wire       board_re_valid;
wire       board_re_err;
wire       board_re_player_id;
wire [2:0] board_re_pit_id;
wire [7:0] board_re_nseeds;

wire       board_gg;
wire [7:0] board_player0_score;
wire [7:0] board_player1_score;

reg [3:0] S        , S_nxt;
reg       player_id, player_id_nxt;
reg [2:0] pit_id   , pit_id_nxt;

reg op_fire;
reg re_fire;
reg bop_fire;
reg bre_fire;

board_ctrl b_inst(
    .clk(clk),
    .rst_n(rst_n),
    .op_ready(board_op_ready),
    .op_valid(board_op_valid),
    .op_player_id(board_op_player_id),
    .op_pit_id(board_op_pit_id),
    .op_op(board_op_op),

    .re_ready(board_re_ready),
    .re_valid(board_re_valid),
    .re_err(board_re_err),
    .re_player_id(board_re_player_id),
    .re_pit_id(board_re_pit_id),
    .re_nseeds(board_re_nseeds),

    .gg(board_gg),
    .player0_score(board_player0_score),
    .player1_score(board_player1_score)
);

always @(*) begin
    op_fire = op_valid & op_ready;
    re_fire = re_valid & re_ready;
    bop_fire = board_op_valid & board_op_ready;
    bre_fire = board_re_valid & board_re_ready;

    op_ready_nxt          = op_ready;
    re_valid_nxt          = re_valid;
    re_operr_nxt          = re_operr;
    re_next_player_id_nxt = re_next_player_id;
    re_is_finished_nxt    = re_is_finished;
    re_player0_score_nxt  = re_player0_score;
    re_player1_score_nxt  = re_player1_score;

    player_id_nxt          = player_id;
    pit_id_nxt             = pit_id;

    board_op_valid_nxt     = board_op_valid;
    board_op_player_id_nxt = board_op_player_id;
    board_op_pit_id_nxt    = board_op_pit_id;
    board_op_op_nxt        = board_op_op;

    board_re_ready_nxt     = board_re_ready;

    S_nxt                  = S;
    case (S)
        S_WAIT_OP: begin
            if (op_fire) begin
                op_ready_nxt       = 0;

                player_id_nxt      = op_player_id;
                pit_id_nxt         = op_pit_id;

                board_op_valid_nxt     = /* compelete board control signals here */
                board_op_player_id_nxt = /* compelete board control signals here */
                board_op_pit_id_nxt    = /* compelete board control signals here */
                board_op_op_nxt        = /* compelete board control signals here */

                board_re_ready_nxt = 1;
                S_nxt              = S_LAUNCH_SOW;
            end
            else begin
                op_ready_nxt = 1;
            end
        end
        S_LAUNCH_SOW: begin
            if (bop_fire) begin
                board_op_valid_nxt     = /* compelete board control signals here */
                board_op_player_id_nxt = /* compelete board control signals here */
                board_op_pit_id_nxt    = /* compelete board control signals here */
                board_op_op_nxt        = /* compelete board control signals here */

                board_re_ready_nxt     = 1;
                S_nxt                  = S_SOW;
            end
        end
        S_SOW: begin
            if (bre_fire) begin
                board_re_ready_nxt     = 0;
                if (board_re_err) begin
                    re_valid_nxt = 1;
                    re_operr_nxt = 1;
                    re_next_player_id_nxt = player_id;
                    re_is_finished_nxt = 0;
                    re_player0_score_nxt = 0;
                    re_player1_score_nxt = 0;
                    S_nxt = S_RE;
                end
                else begin
                    if (board_re_player_id == player_id && board_re_nseeds == 1 && board_re_pit_id != 6) begin
                        board_op_valid_nxt     = /* compelete board control signals here */
                        board_op_player_id_nxt = /* compelete board control signals here */
                        board_op_pit_id_nxt    = /* compelete board control signals here */
                        board_op_op_nxt        = /* compelete board control signals here */

                        board_re_ready_nxt     = 1;
                        S_nxt                  = S_LAUNCH_CAPTURE;
                    end
                    else begin
                        re_valid_nxt = 1;
                        re_operr_nxt = 0;
                        re_next_player_id_nxt = (board_re_player_id == player_id && board_re_pit_id == 6) ? player_id : ~player_id;
                        re_is_finished_nxt = board_gg;
                        re_player0_score_nxt = board_gg ? board_player0_score : 0;
                        re_player1_score_nxt = board_gg ? board_player1_score : 0;
                        S_nxt = S_RE;
                    end
                end
            end
        end
        S_RE: begin
            if (re_fire) begin
                op_ready_nxt = 1;

                re_valid_nxt = 0;
                re_operr_nxt = 0;
                re_next_player_id_nxt = 0;
                re_is_finished_nxt = 0;
                S_nxt = S_WAIT_OP;
            end
        end
        S_LAUNCH_CAPTURE: begin
            if (bop_fire) begin
                board_op_valid_nxt     = /* compelete board control signals here */
                board_op_player_id_nxt = /* compelete board control signals here */
                board_op_pit_id_nxt    = /* compelete board control signals here */
                board_op_op_nxt        = /* compelete board control signals here */

                board_re_ready_nxt     = 1;
                S_nxt                  = S_CAPTURE;
            end
        end
        S_CAPTURE: begin
            if (bre_fire) begin
                board_re_ready_nxt     = 0;
                re_valid_nxt           = 1;
                re_operr_nxt           = 0;
                re_next_player_id_nxt  = ~player_id;
                re_is_finished_nxt = board_gg;
                re_player0_score_nxt = board_gg ? board_player0_score : 0;
                re_player1_score_nxt = board_gg ? board_player1_score : 0;
                S_nxt                  = S_RE;
            end
        end
        default: begin
        end
    endcase
end

always @(posedge clk, negedge rst_n) begin
    if (~rst_n) begin
        op_ready <= 0;
        re_valid <= 0;
        re_operr <= 0;
        re_next_player_id <= 0;
        re_is_finished <= 0;
        re_player0_score <= 0;
        re_player1_score <= 0;
        board_op_valid     <= /* compelete board control signals initialization here */
        board_op_player_id <= /* compelete board control signals initialization here */
        board_op_pit_id    <= /* compelete board control signals initialization here */
        board_op_op        <= /* compelete board control signals initialization here */
        board_re_ready <= 0;
        S <= S_WAIT_OP;
        player_id <= 0;
        pit_id <= 0;
    end
    else begin
        op_ready           <= op_ready_nxt           ;
        re_valid           <= re_valid_nxt           ;
        re_operr           <= re_operr_nxt           ;
        re_next_player_id  <= re_next_player_id_nxt  ;
        re_is_finished     <= re_is_finished_nxt     ;
        re_player0_score   <= re_player0_score_nxt   ;
        re_player1_score   <= re_player1_score_nxt   ;
        board_op_valid     <= board_op_valid_nxt     ;
        board_op_player_id <= board_op_player_id_nxt ;
        board_op_pit_id    <= board_op_pit_id_nxt    ;
        board_op_op        <= board_op_op_nxt        ;
        board_re_ready     <= board_re_ready_nxt     ;
        S                  <= S_nxt                  ;
        player_id          <= player_id_nxt          ;
        pit_id             <= pit_id_nxt             ;
    end
end

always @(*) begin
    
end

endmodule

module board_ctrl (
    input        clk,
    input        rst_n,
    output reg   op_ready,
    input        op_valid,
    input        op_player_id,
    input [2:0]  op_pit_id,
    input [1:0]  op_op,

    input            re_ready,
    output reg       re_valid,
    output reg       re_err,
    output reg       re_player_id,
    output reg [2:0] re_pit_id,
    output reg [7:0] re_nseeds,
    
    output reg       gg,
    output reg [7:0] player0_score,
    output reg [7:0] player1_score
);

localparam BOP_N   = 0,
           BOP_SOW = 1,
           BOP_CAP = 2,
           BOP_RST = 3;

localparam S_IDLE = 0,
           S_SOW = 1,
           S_CAP = 2,
           S_RE = 3;

reg      op_ready_nxt;

reg      re_valid_nxt;
reg      re_err_nxt;
reg      re_player_id_nxt;
reg [2:0] re_pit_id_nxt;
reg [7:0] re_nseeds_nxt;

reg [3:0] S, S_nxt;

reg [7:0] P0[0:6]/* verilator public */;
reg [7:0] P1[0:6]/* verilator public */;
reg [7:0] P0_nxt[0:6];
reg [7:0] P1_nxt[0:6];

reg       player_id, player_id_nxt;
reg [2:0] pit_id   , pit_id_nxt;
reg [1:0] op       , op_nxt;
reg [7:0] nseeds   , nseeds_nxt;

reg       sowing_player_id , sowing_player_id_nxt;
reg [2:0] sowing_pit_id    , sowing_pit_id_nxt;
reg       last_sowing_player_id , last_sowing_player_id_nxt;
reg [2:0] last_sowing_pit_id    , last_sowing_pit_id_nxt;

reg op_fire;
reg re_fire;

reg [5:0] P0_zero;
reg [5:0] P1_zero;

integer i;

always @(*) begin

    op_fire = op_valid & op_ready;
    re_fire = re_valid & re_ready;

    for (i = 0; i < 6; i = i + 1) begin
        P0_zero[i] = ~| P0[i];
        P1_zero[i] = ~| P1[i];
    end

    op_ready_nxt = op_ready;

    re_valid_nxt = re_valid;
    re_err_nxt = re_err;
    re_player_id_nxt = re_player_id;
    re_pit_id_nxt = re_pit_id;
    re_nseeds_nxt = re_nseeds;

    sowing_player_id_nxt = sowing_player_id;
    sowing_pit_id_nxt    = sowing_pit_id;
    last_sowing_player_id_nxt = last_sowing_player_id;
    last_sowing_pit_id_nxt    = last_sowing_pit_id;

    S_nxt = S;

    for (i = 0; i < 7; i = i + 1) begin
        P0_nxt[i] = P0[i];
        P1_nxt[i] = P1[i];
    end

    player_id_nxt = player_id;
    pit_id_nxt    = pit_id;
    op_nxt        = op;
    nseeds_nxt    = nseeds;

    case (S)
        S_IDLE: begin
            if (op_fire) begin
                op_ready_nxt = 0;

                player_id_nxt = op_player_id;
                pit_id_nxt    = op_pit_id;
                op_nxt        = op_op;
                if (op_op == BOP_SOW) begin
                    if (op_pit_id == 6) begin
                        re_valid_nxt = 1;
                        re_err_nxt = 1;
                        re_player_id_nxt = 0;
                        re_pit_id_nxt = 0;
                        re_nseeds_nxt = 0;
                        S_nxt = S_RE;
                    end
                    else begin
                        sowing_player_id_nxt = op_player_id;
                        sowing_pit_id_nxt = op_pit_id + 1;
                        for (i = 0; i < 6; i = i + 1) begin
                            P0_nxt[i] = (op_player_id == 0 && op_pit_id == i) ? 0 : P0[i];
                            P1_nxt[i] = (op_player_id == 1 && op_pit_id == i) ? 0 : P1[i];
                        end
                        if (op_player_id) begin
                            nseeds_nxt = P1[op_pit_id];
                        end
                        else begin
                            nseeds_nxt = P0[op_pit_id];
                        end
                        S_nxt = S_SOW;
                    end
                end
                else if (op_op == BOP_CAP) begin
                    S_nxt = S_CAP;
                end
            end
            else begin
                op_ready_nxt = 1;
            end
        end
        S_SOW: begin
            if (nseeds == 0) begin
                re_valid_nxt = 1;
                re_err_nxt = 0;
                re_player_id_nxt = last_sowing_player_id;
                re_pit_id_nxt = last_sowing_pit_id;
                re_nseeds_nxt = last_sowing_player_id ? P1[last_sowing_pit_id] : P0[last_sowing_pit_id];
                S_nxt = S_RE;
            end
            else begin
                sowing_player_id_nxt = (sowing_pit_id == 6) ? ~sowing_player_id : sowing_player_id;
                sowing_pit_id_nxt    = (sowing_pit_id == 6) ? 0 : sowing_pit_id + 1;
                nseeds_nxt           = (sowing_pit_id == 6 && sowing_player_id == ~player_id) ? nseeds : nseeds - 1;
                for (i = 0; i < 6; i = i + 1) begin
                    // sowing_pit_id: the next pit to drop a seed in this sow
                    // sowing_player_id: the current player
                    // 
                    P0_nxt[i] = /* hint: in each drop, a pit either gets a seed(P0[i] + 1) or keeps the number of seeds (P0[i]). What's the criteria? */
                    P1_nxt[i] = /* hint: in each drop, a pit either gets a seed(P1[i] + 1) or keeps the number of seeds (P1[i]). What's the criteria? */
                end
                P0_nxt[6] = ((player_id == 0) && (sowing_pit_id == 6 && sowing_player_id == 0)) ? P0[i] + 1: P0[i];
                P1_nxt[6] = ((player_id == 1) && (sowing_pit_id == 6 && sowing_player_id == 1)) ? P1[i] + 1: P1[i];
                if (nseeds == 1) begin
                    last_sowing_player_id_nxt = sowing_player_id;
                    last_sowing_pit_id_nxt = sowing_pit_id;
                end
                S_nxt = S_SOW;
            end
        end
        S_CAP: begin
            if (player_id == 0) begin
                P0_nxt[6] = P0[6] + P0[pit_id] + P1[5-pit_id];
                for (i = 0; i < 6; i = i + 1) begin
                    // pit_id: the pit id which the capture operation choose.
                    P1_nxt[i] = /* How to remove the opposite pit? What's the id? */
                    P0_nxt[i] = (pit_id == i) ? 0 : P0[i];
                end
            end
            if (player_id == 1) begin
                P1_nxt[6] = P1[6] + P1[pit_id] + P0[5-pit_id];
                for (i = 0; i < 6; i = i + 1) begin
                    // pit_id: the pit id which the capture operation choose.
                    P0_nxt[i] = /* How to remove the opposite pit? What's the id? */
                    P1_nxt[i] = (pit_id == i) ? 0 : P1[i];
                end
            end
            re_valid_nxt = 1;
            re_err_nxt = 0;
            re_player_id_nxt = player_id;
            re_pit_id_nxt = pit_id;
            re_nseeds_nxt = 0;
            S_nxt = S_RE;
        end
        S_RE: begin
            if (re_fire) begin
                op_ready_nxt = 1;

                re_valid_nxt = 0;
                re_err_nxt = 0;
                re_player_id_nxt = 0;
                re_pit_id_nxt = 0;
                re_nseeds_nxt = 0;

                if (gg) begin
                    for (i = 0; i < 6; i = i + 1) begin
                        P0_nxt[i] = 4;
                        P1_nxt[i] = 4; 
                    end
                    P0_nxt[6] = 0;
                    P1_nxt[6] = 0; 
                end

                S_nxt = S_IDLE;
            end
        end
        default: begin
        end
    endcase
end

always @(posedge clk, negedge rst_n) begin
    if (~rst_n) begin
        op_ready <= 0;

        re_valid <= 0;
        re_err <= 0;
        re_player_id <= 0;
        re_pit_id <= 0;
        re_nseeds <= 0;
        S <= 0;

        for (i = 0; i < 6; i = i + 1) begin
            P0[i] <= 4;
            P1[i] <= 4; 
        end
        P0[6] <= 0;
        P1[6] <= 0;

        player_id <= 0;
        pit_id    <= 0;
        op        <= 0;
        nseeds    <= 0;

        sowing_player_id <= 0;
        sowing_pit_id <= 0;
        last_sowing_player_id <= 0;
        last_sowing_pit_id <= 0;
    end
    else begin
        op_ready <= op_ready_nxt;

        re_valid <= re_valid_nxt;
        re_err <= re_err_nxt;
        re_player_id <= re_player_id_nxt;
        re_pit_id <= re_pit_id_nxt;
        re_nseeds <= re_nseeds_nxt;
        S <= S_nxt;

        for (i = 0; i < 7; i = i + 1) begin
           P0[i] <= P0_nxt[i];
           P1[i] <= P1_nxt[i];
        end

        player_id <= player_id_nxt;
        pit_id    <= pit_id_nxt;
        op        <= op_nxt;
        nseeds    <= nseeds_nxt;

        sowing_player_id <= sowing_player_id_nxt;
        sowing_pit_id    <= sowing_pit_id_nxt;
        last_sowing_player_id <= last_sowing_player_id_nxt;
        last_sowing_pit_id    <= last_sowing_pit_id_nxt;
    end
end

always @(*) begin
    gg = (& P0_zero) || (& P1_zero);
    player0_score = P0[6] + P0[0] + P0[1] + P0[2] + P0[3] + P0[4] + P0[5];
    player1_score = P1[6] + P1[0] + P1[1] + P1[2] + P1[3] + P1[4] + P1[5];
end

endmodule

dlab_kalah/golden/player1win.vcd
$version Generated by VerilatedVcd $end
$timescale 1ps $end
 $scope module TOP $end
  $scope module kalah $end
   $var wire 1 0 clk $end
   $var wire 1 1 rst_n $end
   $var wire 1 2 op_ready $end
   $var wire 1 3 op_valid $end
   $var wire 1 4 op_player_id $end
   $var wire 3 5 op_pit_id [2:0] $end
   $var wire 1 6 re_ready $end
   $var wire 1 7 re_valid $end
   $var wire 1 8 re_operr $end
   $var wire 1 9 re_next_player_id $end
   $var wire 1 : re_is_finished $end
   $var wire 8 ; re_player0_score [7:0] $end
   $var wire 8 < re_player1_score [7:0] $end
   $var wire 1 = op_ready_nxt $end
   $var wire 1 > re_valid_nxt $end
   $var wire 1 ? re_operr_nxt $end
   $var wire 1 @ re_next_player_id_nxt $end
   $var wire 1 A re_is_finished_nxt $end
   $var wire 8 B re_player0_score_nxt [7:0] $end
   $var wire 8 C re_player1_score_nxt [7:0] $end
   $var wire 32 L! S_WAIT_OP [31:0] $end
   $var wire 32 M! S_ERR_OP [31:0] $end
   $var wire 32 N! S_LAUNCH_SOW [31:0] $end
   $var wire 32 O! S_SOW [31:0] $end
   $var wire 32 P! S_LAUNCH_CAPTURE [31:0] $end
   $var wire 32 Q! S_CAPTURE [31:0] $end
   $var wire 32 R! S_RE [31:0] $end
   $var wire 32 L! BOP_N [31:0] $end
   $var wire 32 M! BOP_SOW [31:0] $end
   $var wire 32 N! BOP_CAP [31:0] $end
   $var wire 32 O! BOP_RST [31:0] $end
   $var wire 1 D board_op_ready $end
   $var wire 1 E board_op_valid $end
   $var wire 1 F board_op_valid_nxt $end
   $var wire 1 G board_op_player_id $end
   $var wire 1 H board_op_player_id_nxt $end
   $var wire 3 I board_op_pit_id [2:0] $end
   $var wire 3 J board_op_pit_id_nxt [2:0] $end
   $var wire 2 K board_op_op [1:0] $end
   $var wire 2 L board_op_op_nxt [1:0] $end
   $var wire 1 M board_re_ready $end
   $var wire 1 N board_re_ready_nxt $end
   $var wire 1 O board_re_valid $end
   $var wire 1 P board_re_err $end
   $var wire 1 Q board_re_player_id $end
   $var wire 3 R board_re_pit_id [2:0] $end
   $var wire 8 S board_re_nseeds [7:0] $end
   $var wire 1 T board_gg $end
   $var wire 8 U board_player0_score [7:0] $end
   $var wire 8 V board_player1_score [7:0] $end
   $var wire 4 W S [3:0] $end
   $var wire 4 X S_nxt [3:0] $end
   $var wire 1 Y player_id $end
   $var wire 1 Z player_id_nxt $end
   $var wire 3 [ pit_id [2:0] $end
   $var wire 3 \ pit_id_nxt [2:0] $end
   $var wire 1 ] op_fire $end
   $var wire 1 ^ re_fire $end
   $var wire 1 _ bop_fire $end
   $var wire 1 ` bre_fire $end
   $scope module b_inst $end
    $var wire 1 a clk $end
    $var wire 1 b rst_n $end
    $var wire 1 c op_ready $end
    $var wire 1 d op_valid $end
    $var wire 1 e op_player_id $end
    $var wire 3 f op_pit_id [2:0] $end
    $var wire 2 g op_op [1:0] $end
    $var wire 1 h re_ready $end
    $var wire 1 i re_valid $end
    $var wire 1 j re_err $end
    $var wire 1 k re_player_id $end
    $var wire 3 l re_pit_id [2:0] $end
    $var wire 8 m re_nseeds [7:0] $end
    $var wire 1 n gg $end
    $var wire 8 o player0_score [7:0] $end
    $var wire 8 p player1_score [7:0] $end
    $var wire 32 L! BOP_N [31:0] $end
    $var wire 32 M! BOP_SOW [31:0] $end
    $var wire 32 N! BOP_CAP [31:0] $end
    $var wire 32 O! BOP_RST [31:0] $end
    $var wire 32 L! S_IDLE [31:0] $end
    $var wire 32 M! S_SOW [31:0] $end
    $var wire 32 N! S_CAP [31:0] $end
    $var wire 32 O! S_RE [31:0] $end
    $var wire 1 q op_ready_nxt $end
    $var wire 1 r re_valid_nxt $end
    $var wire 1 s re_err_nxt $end
    $var wire 1 t re_player_id_nxt $end
    $var wire 3 u re_pit_id_nxt [2:0] $end
    $var wire 8 v re_nseeds_nxt [7:0] $end
    $var wire 4 w S [3:0] $end
    $var wire 4 x S_nxt [3:0] $end
    $var wire 8 y P0[0] [7:0] $end
    $var wire 8 z P0[1] [7:0] $end
    $var wire 8 { P0[2] [7:0] $end
    $var wire 8 | P0[3] [7:0] $end
    $var wire 8 } P0[4] [7:0] $end
    $var wire 8 ~ P0[5] [7:0] $end
    $var wire 8 !! P0[6] [7:0] $end
    $var wire 8 "! P1[0] [7:0] $end
    $var wire 8 #! P1[1] [7:0] $end
    $var wire 8 $! P1[2] [7:0] $end
    $var wire 8 %! P1[3] [7:0] $end
    $var wire 8 &! P1[4] [7:0] $end
    $var wire 8 '! P1[5] [7:0] $end
    $var wire 8 (! P1[6] [7:0] $end
    $var wire 8 )! P0_nxt[0] [7:0] $end
    $var wire 8 *! P0_nxt[1] [7:0] $end
    $var wire 8 +! P0_nxt[2] [7:0] $end
    $var wire 8 ,! P0_nxt[3] [7:0] $end
    $var wire 8 -! P0_nxt[4] [7:0] $end
    $var wire 8 .! P0_nxt[5] [7:0] $end
    $var wire 8 /! P0_nxt[6] [7:0] $end
    $var wire 8 0! P1_nxt[0] [7:0] $end
    $var wire 8 1! P1_nxt[1] [7:0] $end
    $var wire 8 2! P1_nxt[2] [7:0] $end
    $var wire 8 3! P1_nxt[3] [7:0] $end
    $var wire 8 4! P1_nxt[4] [7:0] $end
    $var wire 8 5! P1_nxt[5] [7:0] $end
    $var wire 8 6! P1_nxt[6] [7:0] $end
    $var wire 1 7! player_id $end
    $var wire 1 8! player_id_nxt $end
    $var wire 3 9! pit_id [2:0] $end
    $var wire 3 :! pit_id_nxt [2:0] $end
    $var wire 2 ;! op [1:0] $end
    $var wire 2 <! op_nxt [1:0] $end
    $var wire 8 =! nseeds [7:0] $end
    $var wire 8 >! nseeds_nxt [7:0] $end
    $var wire 1 ?! sowing_player_id $end
    $var wire 1 @! sowing_player_id_nxt $end
    $var wire 3 A! sowing_pit_id [2:0] $end
    $var wire 3 B! sowing_pit_id_nxt [2:0] $end
    $var wire 1 C! last_sowing_player_id $end
    $var wire 1 D! last_sowing_player_id_nxt $end
    $var wire 3 E! last_sowing_pit_id [2:0] $end
    $var wire 3 F! last_sowing_pit_id_nxt [2:0] $end
    $var wire 1 G! op_fire $end
    $var wire 1 H! re_fire $end
    $var wire 6 I! P0_zero [5:0] $end
    $var wire 6 J! P1_zero [5:0] $end
    $var wire 32 K! i [31:0] $end
   $upscope $end
  $upscope $end
  $var wire 1 # clk $end
  $var wire 1 $ rst_n $end
  $var wire 1 % op_ready $end
  $var wire 1 & op_valid $end
  $var wire 1 ' op_player_id $end
  $var wire 3 ( op_pit_id [2:0] $end
  $var wire 1 ) re_ready $end
  $var wire 1 * re_valid $end
  $var wire 1 + re_operr $end
  $var wire 1 , re_next_player_id $end
  $var wire 1 - re_is_finished $end
  $var wire 8 . re_player0_score [7:0] $end
  $var wire 8 / re_player1_score [7:0] $end
 $upscope $end
$enddefinitions $end


#5
0#
0$
0%
0&
0'
b000 (
0)
0*
0+
0,
0-
b00000000 .
b00000000 /
00
01
02
03
04
b000 5
06
07
08
09
0:
b00000000 ;
b00000000 <
1=
0>
0?
0@
0A
b00000000 B
b00000000 C
0D
0E
0F
0G
0H
b000 I
b000 J
b00 K
b00 L
0M
0N
0O
0P
0Q
b000 R
b00000000 S
1T
b00000000 U
b00000000 V
b0000 W
b0000 X
0Y
0Z
b000 [
b000 \
0]
0^
0_
0`
0a
0b
0c
0d
0e
b000 f
b00 g
0h
0i
0j
0k
b000 l
b00000000 m
1n
b00000000 o
b00000000 p
1q
0r
0s
0t
b000 u
b00000000 v
b0000 w
b0000 x
b00000000 y
b00000000 z
b00000000 {
b00000000 |
b00000000 }
b00000000 ~
b00000000 !!
b00000000 "!
b00000000 #!
b00000000 $!
b00000000 %!
b00000000 &!
b00000000 '!
b00000000 (!
b00000000 )!
b00000000 *!
b00000000 +!
b00000000 ,!
b00000000 -!
b00000000 .!
b00000000 /!
b00000000 0!
b00000000 1!
b00000000 2!
b00000000 3!
b00000000 4!
b00000000 5!
b00000000 6!
07!
08!
b000 9!
b000 :!
b00 ;!
b00 <!
b00000000 =!
b00000000 >!
0?!
0@!
b000 A!
b000 B!
0C!
0D!
b000 E!
b000 F!
0G!
0H!
b111111 I!
b111111 J!
b00000000000000000000000000000111 K!
b00000000000000000000000000000000 L!
b00000000000000000000000000000001 M!
b00000000000000000000000000000010 N!
b00000000000000000000000000000011 O!
b00000000000000000000000000000100 P!
b00000000000000000000000000000101 Q!
b00000000000000000000000000000110 R!
#10
1#
10
0T
b00011000 U
b00011000 V
1a
0n
b00011000 o
b00011000 p
b00000100 y
b00000100 z
b00000100 {
b00000100 |
b00000100 }
b00000100 ~
b00000100 "!
b00000100 #!
b00000100 $!
b00000100 %!
b00000100 &!
b00000100 '!
b00000100 )!
b00000100 *!
b00000100 +!
b00000100 ,!
b00000100 -!
b00000100 .!
b00000100 0!
b00000100 1!
b00000100 2!
b00000100 3!
b00000100 4!
b00000100 5!
b000000 I!
b000000 J!
#15
0#
00
0a
#20
1#
10
1a
#25
0#
1$
00
11
0a
1b
#30
1#
1%
10
12
1D
1a
1c
#35
0#
00
0a
#40
1#
10
1a
#45
0#
1&
b010 (
00
13
b010 5
0=
1F
b010 J
b01 L
1N
b0010 X
b010 \
1]
0a
#50
1#
0%
10
02
1E
0F
b010 I
b000 J
b01 K
b00 L
1M
b0010 W
b0011 X
b010 [
0]
1_
1a
1d
b010 f
b01 g
1h
0q
b0001 x
b00000000 +!
b010 :!
b01 <!
b00000100 >!
b011 B!
1G!
b00000000000000000000000000000110 K!
#55
0#
0&
1)
00
03
16
0a
#60
1#
10
0D
0E
b000 I
b00 K
b00010100 V
b0011 W
0_
1a
0c
0d
b000 f
b00 g
b00010100 p
b0001 w
b00000000 {
b00000101 ,!
b010 9!
b01 ;!
b00000100 =!
b00000011 >!
b011 A!
b100 B!
0G!
b000100 I!
#65
0#
00
0a
#70
1#
10
b00010101 V
1a
b00010101 p
b00000101 |
b00000101 -!
b00000011 =!
b00000010 >!
b100 A!
b101 B!
#75
0#
00
0a
#80
1#
10
b00010110 V
1a
b00010110 p
b00000101 }
b00000101 .!
b00000010 =!
b00000001 >!
b101 A!
b110 B!
#85
0#
00
0a
#90
1#
10
b00010111 V
1a
b00010111 p
b00000101 ~
b00000001 /!
b00000001 =!
b00000000 >!
1@!
b110 A!
b000 B!
b110 F!
#95
0#
00
0a
#100
1#
10
b00011001 U
1a
b00011001 o
1r
b110 u
b00000001 v
b0011 x
b00000001 !!
b00000000 =!
1?!
b000 A!
b110 E!
b00000000000000000000000000000111 K!
#105
0#
00
0a
#110
1#
10
1>
0N
1O
b110 R
b00000001 S
b0110 X
1`
1a
1i
b110 l
b00000001 m
1q
0r
b000 u
b00000000 v
b0011 w
b0000 x
1H!
#115
0#
00
0a
#120
1#
1*
10
17
1=
0>
1D
0M
0O
b000 R
b00000000 S
b0110 W
b0000 X
1^
0`
1a
1c
0h
0i
b000 l
b00000000 m
b0000 w
0H!
#125
0#
00
0a
#130
1#
1%
0*
10
12
07
b0000 W
0^
1a
#135
0#
0)
00
06
0a
#140
1#
10
1a
#145
0#
00
0a
#150
1#
10
1a
#155
0#
00
0a
#160
1#
10
1a
#165
0#
1&
b011 (
00
13
b011 5
0=
1F
b011 J
b01 L
1N
b0010 X
b011 \
1]
0a
#170
1#
0%
10
02
1E
0F
b011 I
b000 J
b01 K
b00 L
1M
b0010 W
b0011 X
b011 [
0]
1_
1a
1d
b011 f
b01 g
1h
0q
b0001 x
b00000000 ,!
b011 :!
b00000101 >!
0@!
b100 B!
1G!
b00000000000000000000000000000110 K!
#175
0#
0&
1)
00
03
16
0a
#180
1#
10
0D
0E
b000 I
b00 K
b00010010 V
b0011 W
0_
1a
0c
0d
b000 f
b00 g
b00010010 p
b0001 w
b00000000 |
b00000110 -!
b011 9!
b00000101 =!
b00000100 >!
0?!
b100 A!
b101 B!
0G!
b001100 I!
#185
0#
00
0a
#190
1#
10
b00010011 V
1a
b00010011 p
b00000110 }
b00000110 .!
b00000100 =!
b00000011 >!
b101 A!
b110 B!
#195
0#
00
0a
#200
1#
10
b00010100 V
1a
b00010100 p
b00000110 ~
b00000010 /!
b00000011 =!
b00000010 >!
1@!
b110 A!
b000 B!
#205
0#
00
0a
#210
1#
10
b00011010 U
1a
b00011010 o
b00000010 !!
b00000101 0!
b00000010 =!
b00000001 >!
1?!
b000 A!
b001 B!
#215
0#
00
0a
#220
1#
10
b00011011 U
1a
b00011011 o
b00000101 "!
b00000101 1!
b00000001 =!
b00000000 >!
b001 A!
b010 B!
1D!
b001 F!
#225
0#
00
0a
#230
1#
10
b00011100 U
1a
b00011100 o
1r
1t
b001 u
b00000101 v
b0011 x
b00000101 #!
b00000000 =!
b010 A!
1C!
b001 E!
b00000000000000000000000000000111 K!
#235
0#
00
0a
#240
1#
10
1>
1@
0N
1O
1Q
b001 R
b00000101 S
b0110 X
1`
1a
1i
1k
b001 l
b00000101 m
1q
0r
0t
b000 u
b00000000 v
b0011 w
b0000 x
1H!
#245
0#
00
0a
#250
1#
1*
1,
10
17
19
1=
0>
0@
1D
0M
0O
0Q
b000 R
b00000000 S
b0110 W
b0000 X
1^
0`
1a
1c
0h
0i
0k
b000 l
b00000000 m
b0000 w
0H!
#255
0#
00
0a
#260
1#
1%
0*
0,
10
12
07
09
b0000 W
0^
1a
#265
0#
0)
00
06
0a
#270
1#
10
1a
#275
0#
00
0a
#280
1#
10
1a
#285
0#
00
0a
#290
1#
10
1a
#295
0#
1&
1'
b010 (
00
13
14
b010 5
0=
1F
1H
b010 J
b01 L
1N
b0010 X
1Z
b010 \
1]
0a
#300
1#
0%
10
02
1E
0F
1G
0H
b010 I
b000 J
b01 K
b00 L
1M
b0010 W
b0011 X
1Y
b010 [
0]
1_
1a
1d
1e
b010 f
b01 g
1h
0q
b0001 x
b00000000 2!
18!
b010 :!
b00000100 >!
b011 B!
1G!
b00000000000000000000000000000110 K!
#305
0#
0&
1)
00
03
16
0a
#310
1#
10
0D
0E
0G
b000 I
b00 K
b00011000 U
b0011 W
0_
1a
0c
0d
0e
b000 f
b00 g
b00011000 o
b0001 w
b00000000 $!
b00000101 3!
17!
b010 9!
b00000100 =!
b00000011 >!
b011 A!
b100 B!
0G!
b000100 J!
#315
0#
00
0a
#320
1#
10
b00011001 U
1a
b00011001 o
b00000101 %!
b00000101 4!
b00000011 =!
b00000010 >!
b100 A!
b101 B!
#325
0#
00
0a
#330
1#
10
b00011010 U
1a
b00011010 o
b00000101 &!
b00000101 5!
b00000010 =!
b00000001 >!
b101 A!
b110 B!
#335
0#
00
0a
#340
1#
10
b00011011 U
1a
b00011011 o
b00000101 '!
b00000001 6!
b00000001 =!
b00000000 >!
0@!
b110 A!
b000 B!
b110 F!
#345
0#
00
0a
